[{"retweet_text": "gigaom.com\u90fdc\u8f6e\u4e86\uff0c\u878d\u4e861150\u4e07\u7f8e\u5143\uff0c\u673a\u5668\u5b66\u4e60\u65e5\u62a5\u5927\u6709\u53ef\u4e3a\u554a\u3002\u6211\u8d76\u7d27\u628apullcore\u641e\u641e\u4e5f\u505a\u4e2a\u4e2d\u56fd\u7248gigaom\u5427\uff0c\u63d0\u524d\u57cb\u4f0f\u597d\u3002", "post_time": "2015-01-02", "retweet_poster_link": "http://weibo.com/1497035431", "text": " //@\u6881\u658cpenny:\u5927\u5bb6\u4e0d\u8981\u5c0f\u770bgigaom\uff0c\u7f8e\u519b\u4e0d\u53ea\u662f\u6709hacknews\u3002\u5176\u5b9e\u8fd9\u7c7bnarrative science\u578b\u516c\u53f8\uff0c\u4e00\u822c\u9762\u5411\u7684\u662f\u4e00\u4e9b\u5c0f\u8d44\u767d\u9886\uff0c\u5e73\u5e38\u7d2f\u5f97\ud83d\udc36\u4e00\u6837\uff0c\u665a\u4e0a10\u70b9\u6458\u8981\u6027\u7684\u770b\u770b\u4e1a\u754c\u53d1\u751f\u4e86\u4ec0\u4e48\u4e8b\u3002\u6216\u8005\u65b9\u4fbf\u7684\u65f6\u5019\u770b\u770b\u3002", "poster_name": "@\u5b59\u660e\u660e_SmarterChina", "profile_photo": "http://tp3.sinaimg.cn/1914450674/50/5644229416/1", "poster_link": "http://weibo.com/1914450674", "retweet_poster_name": "@\u6881\u658cpenny", "original_link": "http://weibo.com/1914450674/BDEWhn3ki"}, {"post_time": "2015-01-02", "text": "\u3010 GNU Screen \u5feb\u901f\u53c2\u8003\u3011<a href=\"http://t.cn/bHxzX\" target=\"_blank\">http://t.cn/bHxzX</a> GNU Screen\u662f\u4e00\u6b3e\u7531GNU\u8ba1\u5212\u5f00\u53d1\u7684\u7528\u4e8e\u547d\u4ee4\u884c\u7ec8\u7aef\u5207\u6362\u7684\u81ea\u7531\u8f6f\u4ef6\u3002\u7528\u6237\u53ef\u4ee5\u901a\u8fc7\u8be5\u8f6f\u4ef6\u540c\u65f6\u8fde\u63a5\u591a\u4e2a\u672c\u5730\u6216\u8fdc\u7a0b\u7684\u547d\u4ee4\u884c\u4f1a\u8bdd\uff0c\u5e76\u5728\u5176\u95f4\u81ea\u7531\u5207\u6362\u3002\u8f6c\u9700\uff01", "poster_name": "@\u7f51\u8def\u51b7\u773c", "profile_photo": "http://tp3.sinaimg.cn/1715118170/50/5653230631/1", "poster_link": "http://weibo.com/1715118170", "original_link": "http://weibo.com/1715118170/BDEqvlaJg"}, {"post_time": "2015-01-02", "text": "\u673a\u5668\u5b66\u4e60\u65e5\u62a5 2015-01-01 <a href=\"http://t.cn/RZbssmw\" target=\"_blank\">http://t.cn/RZbssmw</a> 1) \u5927\u6570\u636e\u5206\u6790\u5230\u5e95\u9700\u8981\u591a\u5c11\u79cd\u5de5\u5177\uff1f 2) \u673a\u5668\u4eba\u80fd\u4e0d\u80fd\u8003\u4e0a\u5927\u5b66\uff1f 3) \u8c37\u6b4c\u667a\u80fd\u8f66\u7684\u96be\u70b9\u5728\u54ea\u91cc\uff1f 4) Pairwise Learning to Rank\u5de5\u5177\u603b\u7ed3 5) Nature\uff1aR\u8bed\u8a00\u4ecb\u7ecd \u53ef\u70b9\u51fb\u52a0\u957f\u724823\u6761 <a href=\"http://t.cn/RZGvPNt\" target=\"_blank\">http://t.cn/RZGvPNt</a>", "poster_name": "@\u597d\u4e1c\u897f\u4f20\u9001\u95e8", "profile_photo": "http://tp1.sinaimg.cn/5220650532/50/5701668539/1", "poster_link": "http://weibo.com/5220650532", "original_link": "http://weibo.com/5220650532/BDEnbmPDY"}, {"post_time": "2015-01-02", "text": "\u3010\u673a\u5668\u4eba\u80fd\u4e0d\u80fd\u8003\u4e0a\u5927\u5b66\uff1f\u3011<a href=\"http://t.cn/RZbcIVa\" target=\"_blank\">http://t.cn/RZbcIVa</a> \u674e\u822a\u8001\u5e08\u65b0\u9c9c\u51fa\u7089\u7684\u535a\u5ba2\u3002\u8c8c\u4f3c\u56fd\u5185\u4e5f\u6709\u4eba\u5728\u5f00\u5c55\u673a\u5668\u4eba\u9ad8\u8003\u7684\u7814\u7a76\uff0c\u671f\u5f85\u53d6\u5f97\u7a81\u7834\u3002", "poster_name": "@\u6211\u7231\u673a\u5668\u5b66\u4e60", "profile_photo": "http://tp2.sinaimg.cn/5066241201/50/5690591470/1", "poster_link": "http://weibo.com/5066241201", "original_link": "http://weibo.com/5066241201/BDEfEtv1y"}, {"retweet_text": "\u4e0a\u6d77\u7684\u8e29\u8e0f\u60b2\u5267\u5b8c\u5168\u53ef\u4ee5\u901a\u8fc7\u57fa\u4e8e\u624b\u673a\u6570\u636e\u7684\u57ce\u5e02\u5f02\u5e38\u68c0\u6d4b\u6765\u907f\u514d\u3002\u5f53\u53d1\u73b0\u4eba\u6d41\u8fc7\u4e8e\u805a\u96c6\u5e76\u4e14\u79fb\u52a8\u6ede\u7559\uff0c\u5c31\u53ef\u4ee5\u63d0\u524d\u9884\u8b66\u548c\u758f\u6563\u3002\u5728#\u57ce\u5e02\u8ba1\u7b97#\u9886\u57df\u76f8\u5173\u7684\u7814\u7a76\u5df2\u7ecf\u6210\u719f\u3002\u4ee5\u524d\u6211\u8fd8\u5e38\u62ff\u5fb7\u56fd\u7684\u90a3\u6b21\u8e29\u8e0f\u707e\u96be\u4e3e\u4f8b\uff0c\u5e76\u53d1\u8fc7\u5fae\u535a\u3002\u662f\u65f6\u5019\u52a0\u5feb\u57ce\u5e02\u8ba1\u7b97\u7684\u4ea7\u4e1a\u5316\u4e86\u3002", "post_time": "2015-01-02", "retweet_poster_link": "http://weibo.com/2073091511", "text": "\u5173\u4e8e\u5f02\u5e38\u68c0\u6d4b\uff0c\u6211\u4eec\u4ee5\u524d\u63a8\u8350\u8fc7\u5341\u591a\u4e2a\u8d44\u6e90\uff1a<a href=\"http://t.cn/RPHVQxI\" target=\"_blank\">http://t.cn/RPHVQxI</a> \u7279\u522b\u662f\u97e9\u5bb6\u4f1f\u8001\u5e08\u7684\u5f02\u5e38\u68c0\u6d4b\u8bb2\u4e49 <a href=\"http://t.cn/RPT45uN\" target=\"_blank\">http://t.cn/RPT45uN</a>", "poster_name": "@\u597d\u4e1c\u897f\u4f20\u9001\u95e8", "profile_photo": "http://tp1.sinaimg.cn/5220650532/50/5701668539/1", "poster_link": "http://weibo.com/5220650532", "retweet_poster_name": "@\u90d1\u5b87MSRA", "original_link": "http://weibo.com/5220650532/BDEfbyZpx"}, {"post_time": "2015-01-02", "text": "2014\u5e74\u5ea6\uff0c\u4f2f\u4e50\u5728\u7ebf\u535a\u5ba2\u70ed\u95e8\u6587\u7ae0\uff1a\u300a\u8001\u7801\u519c\u5192\u6b7b\u63ed\u5f00\u884c\u4e1a\u9ed1\u5e55\uff1a\u5982\u4f55\u7f16\u5199\u65e0\u6cd5\u7ef4\u62a4\u7684\u4ee3\u7801\u300b<a href=\"http://t.cn/RzbxYws\" target=\"_blank\">http://t.cn/RzbxYws</a>\u300a\u5982\u679c\u770b\u4e86\u6b64\u6587\u8fd8\u4e0d\u61c2\u5085\u91cc\u53f6\u53d8\u6362\uff0c\u90a3\u5c31\u8fc7\u6765\u6390\u6b7b\u6211\u5427\u300b<a href=\"http://t.cn/Rvih5M8\" target=\"_blank\">http://t.cn/Rvih5M8</a>\u300a\u56fd\u5916\u7a0b\u5e8f\u5458\u6574\u7406\u7684 C++ \u8d44\u6e90\u5927\u5168\u300b<a href=\"http://t.cn/R7IZbhO\" target=\"_blank\">http://t.cn/R7IZbhO</a>\u300a\u8eab\u4e3a\u7801\u519c\uff0c\u4e3a12306\u8bf4\u4e24\u53e5\u516c\u9053\u8bdd\u300b<a href=\"http://t.cn/8Fw7rbe\" target=\"_blank\">http://t.cn/8Fw7rbe</a>", "poster_name": "@\u4f2f\u4e50\u5728\u7ebf\u5b98\u65b9\u5fae\u535a", "profile_photo": "http://tp2.sinaimg.cn/1670481425/50/1286328769/1", "poster_link": "http://weibo.com/1670481425", "original_link": "http://weibo.com/1670481425/BDEenhwe0"}, {"img_size": "175,300", "text": "\u3010\u7528Docker\u6784\u5efaRPM\u3011<a href=\"http://t.cn/RZUndX8\" target=\"_blank\">http://t.cn/RZUndX8</a> \u5173\u4e8eDocker\u548cRPM\u7684\u6587\u7ae0\u3002\u8f6c\u9700\uff01", "poster_name": "@\u7f51\u8def\u51b7\u773c", "profile_photo": "http://tp3.sinaimg.cn/1715118170/50/5653230631/1", "poster_link": "http://weibo.com/1715118170", "post_time": "2015-01-02", "img_url": "http://ww4.sinaimg.cn/large/663aa05ajw1enuwri7ogxj204v08cq2w.jpg", "original_link": "http://weibo.com/1715118170/BDEebvlma"}, {"post_time": "2015-01-02", "text": "#\u4e00\u5929\u4e00\u7bc7\u8bfb\u540e\u611f#\uff0c\u4e00\u6708\u4e8c\u65e5\uff0cNaiad: A Timely Dataflow System \u7eed\u3002\u6709\u540c\u5b66 (@didi10000) \u8bc4\u8bba\uff0c\u867d\u7136\u611f\u89c9Naiad\u597d\uff0c\u4f46\u662f\u5e76\u4e0d\u4e86\u89e3\u4e3a\u4ec0\u4e48\u3002\u5176\u5b9e\u6211\u4e5f\u60f3\u56de\u7b54\u8fd9\u4e2a\u95ee\u9898\uff0c\u4f46\u662f\u65e0\u5948\u4fee\u4e3a\u4e0d\u591f\uff0c\u5e0c\u671b\u6709\u5927\u795e\u5e2e\u5fd9\u3002@\u597d\u4e1c\u897f\u4f20\u9001\u95e8 \u6211\u53d1\u8868\u4e86\u6587\u7ae0 <a href=\"http://t.cn/RZb1Boa\" target=\"_blank\">http://t.cn/RZb1Boa</a>", "poster_name": "@low_accepted", "profile_photo": "http://tp1.sinaimg.cn/1670741644/50/40020984908/1", "poster_link": "http://weibo.com/1670741644", "original_link": "http://weibo.com/1670741644/BDDsQ2Yi1"}, {"retweet_text": "\u5f88\u9ad8\u5174\u4eca\u5929\u4e00\u4e2a\u6821\u53cb\u548c\u6211\u8bf4\uff0c\u5728\u4ed6\u4eec\u751f\u7269\u9886\u57df\u7684\u6570\u636e\u6316\u6398\u95ee\u9898\u5176\u5b9e\u4e5f\u5927\u591a\u662f\u5c0f\u6570\u636e\u95ee\u9898\uff0c\u5927\u6570\u636e\u7684\u5206\u6790\u65b9\u6cd5\u6839\u672c\u4e0d\u7ba1\u7528\uff0e\u8fd8\u662f\u8981\u4eba\u6765\u5f15\u5bfc\uff0c\u628a\u9886\u57df\u77e5\u8bc6\u878d\u5165\u5230\u6a21\u578b\u4e2d\u53bb\uff0e", "post_time": "2015-01-02", "retweet_poster_link": "http://weibo.com/1932835417", "text": "bootstrapping\u548c\u5f31\u76d1\u7763\u5e94\u8be5\u6709\u6548 //@\u6881\u658cpenny: \u6211\u73b0\u5728\u4e3b\u8981\u5957\u8def\u662f\u5927\u91cf\u4f2a\u6807\u6ce8\u8bed\u6599+\u5c11\u90e8\u5206\u4eba\u5de5\u6807\u6ce8\u7684ensemble\u6253\u6cd5\uff0c\u53ea\u662f\u9ec4\u91d1\u6ca1\u6253\u51fa\u591a\u5c11 //@\u9c81\u4e1c\u4e1c\u80d6:\u4e24\u5e74\u524d\u6211\u5bf9\u771f\u6b63\u7684\u5927\u6570\u636e\u4e0a\u7684weakly supervised learning \u548c bootstrapping\u65b9\u6cd5\u5f88\u611f\u5174\u8da3\uff0c\u89c9\u5f97\u8fd9\u79cd\u9ad8\u5ea6\u975e\u7ebf\u6027\u7684filter\u53ef\u4ee5\u627e\u5230\u5927\u6570\u636e\u91cc\u7684\u771f\u6b63\u9ec4\u91d1", "poster_name": "@\u897f\u74dc\u5927\u4e38\u5b50\u6c64", "profile_photo": "http://tp2.sinaimg.cn/1932835417/50/5714878873/1", "poster_link": "http://weibo.com/1932835417", "retweet_poster_name": "@\u897f\u74dc\u5927\u4e38\u5b50\u6c64", "original_link": "http://weibo.com/1932835417/BDDau8sk9"}, {"retweet_text": "2014Top\u79d1\u5b66\u65b0\u95fb\u3002\u6211\u89c9\u5f971\uff0c2\uff0c7\u6700\u6709\u610f\u4e49\u30021\u662f\u767b\u9646\u5f57\u661f\uff0c\u4eba\u7c7b\u767b\u6708\u4ee5\u540e\u8d70\u5411\u5b87\u5b99\u7684\u53c8\u4e00\u5927\u6b65\u30022\u662f\u4eba\u5de5\u5408\u6210\u67d3\u8272\u4f53\uff0c\u63a2\u7d22\u751f\u547d\u8d77\u6e90\u7684\u4e00\u5927\u6b65\u30027\u662f\u8bbe\u8ba1\u7528\u5149\u4ea7\u751f\u7269\u8d28\u3002\u7231\u56e0\u65af\u5766\u7684E=MC^2 \u4f17\u6240\u5468\u77e5\uff0c\u7269\u8d28\u4e0e\u80fd\u91cf\u53ef\u4ee5\u4e92\u6362\u3002\u539f\u5b50\u5f39\u662f\u4ece\u7269\u8d28\u4ea7\u751f\u80fd\u91cf\uff0c\u4f46\u53cd\u65b9\u5411\u4ece\u80fd\u91cf\u4ea7\u751f\u7269\u8d28\u4e00\u76f4\u6ca1\u80fd\u88ab\u9a8c\u8bc1\u3002\u8fd9\u4e2a\u6210\u529f\u4e86\u53ef\u7b97\u4e00\u5927\u7a81\u7834\u3002", "retweet_img_size": "649,559", "post_time": "2015-01-02", "retweet_poster_link": "http://weibo.com/2558582594", "retweet_img_url": "http://ww1.sinaimg.cn/large/9880df42jw1enurpjyll9j20i10fjwgl.jpg", "text": "\u8fd9\u7b2c7\u6761\u76ee\u524d\u53ea\u662f\u4e00\u6761\u8bbe\u8ba1\u30021934\u5e74John Wheeler \u66fe\u7ecf\u63d0\u51fa\u8fc7\u4e00\u4e2a\u8bbe\u60f3\uff0c\u4f46\u4ed6\u4e0d\u8ba4\u4e3a\u4eba\u4eec\u53ef\u4ee5\u5728\u5b9e\u9a8c\u5ba4\u505a\u5230\u3002\u73b0\u5728\u7531\u4e8e\u9ad8\u80fd\u6fc0\u5149\u6280\u672f\u7684\u957f\u8db3\u53d1\u5c55\uff0c\u4f3c\u4e4e\u53ef\u4ee5\u5b9e\u73b0\u4e86\u30022014\u5e74\u4e24\u4e2a\u6ce2\u5170\u7269\u7406\u5b66\u5bb6\u63d0\u51fa\u4e00\u4e2a\u8bbe\u8ba1\uff0c\u9876\u5c16\u7269\u7406\u5b66\u5bb6\u90fd\u8ba4\u4e3a\u53ef\u884c\u3002\u8be6\u60c5\u89c1<a href=\"http://t.cn/RZbudKm\" target=\"_blank\">http://t.cn/RZbudKm</a>", "poster_name": "@\u4e07\u7cbe\u6cb9\u58a8\u7eff", "profile_photo": "http://tp3.sinaimg.cn/2558582594/50/5709096953/1", "poster_link": "http://weibo.com/2558582594", "retweet_poster_name": "@\u4e07\u7cbe\u6cb9\u58a8\u7eff", "original_link": "http://weibo.com/2558582594/BDD9X1iDh"}, {"post_time": "2015-01-02", "text": "\u3010\u6570\u5b66\u90fd\u77e5\u9053\u30112015\u5e741\u67082\u65e5 <a href=\"http://t.cn/RZbmUBf\" target=\"_blank\">http://t.cn/RZbmUBf</a> \u5b89\u65af\u5e93\u59c6\u56db\u91cd\u594f\uff1b\u89e3\u7801\u6bd4\u7279\u5e01\u548c\u5757\u94fe\uff1b\u8ba1\u5212\u7b97\u6cd5\uff1b\u7528\u56fe\u53ef\u89c6\u5316\u76f8\u5173\u6027\uff1bGAP \u2500 \u4e00\u4e2a\u8ba1\u7b97\u79bb\u6563\u4ee3\u6570\u7684\u7cfb\u7edf\uff1b\u5957\u7d22\u7684\u6570\u5b66\uff1b\u5305\u88c5\u6b63\u4e94\u8fb9\u5f62\uff1b\u4e00\u4e2a\u91cf\u5b50\u8ba1\u7b97\u7684\u52a8\u673a\uff1b\u706b\u661f\uff0c\u4e09\u89d2\u5256\u5206\u548cLOMINOES\uff1b\u5e0c\u5c14\u4f2f\u7279\u66f2\u7ebf\u827a\u672f\uff0cHilbertonians\u548c\u7334\u5b50\uff1b\u03c0\uff0c\u03a6\u548ce\u7684\u5706\u8f6e\u827a\u672f\uff1b...", "poster_name": "@Jiang_Xun", "profile_photo": "http://tp3.sinaimg.cn/2496638594/50/5708471468/1", "poster_link": "http://weibo.com/2496638594", "original_link": "http://weibo.com/2496638594/BDCSCjQwt"}, {"retweet_text": "360 \u5b89\u5168\u536b\u58eb for Linux \u4f7f\u7528\u7ed3\u679c <a href=\"http://t.cn/RZ4tiKd\" target=\"_blank\">http://t.cn/RZ4tiKd</a> \u6015\u4e86\u6015\u4e86\u6211\u6015\u4e86", "post_time": "2015-01-01", "retweet_poster_link": "http://weibo.com/2035516367", "text": "windows\u4e0a\u9762\u7684\u5462\uff1f //@phunter_lau:\u53c8\u4e00\u5927\u8089\u9e21\u5e73\u53f0\u554a//@Judgement_Engineer: <a href=\"http://t.cn/RZ4WLAt\" target=\"_blank\">http://t.cn/RZ4WLAt</a> \u6211\u4e0d\u8bf4\u8bdd//@\u6bd4\u5c14\u76d6\u5b50V: \u7528\u6237\u754c\u9762\u7528 root\u2026\u2026//@_\u963f\u9f99_\u7684\u4e00\u4e9b\u4e8b\u4e00\u4e9b\u60c5: //@RednaxelaFX: //@johnhax://@\u6881\u6770_numbbbbb: //@phunter_lau:\u201c\u6ee5\u7528Essential\u6807\u8bb0\u6765\u5236\u9020\u5378\u8f7d\u7684\u9ebb\u70e6\u201d\uff0c\u592a\u673a\u667a\u4e86", "poster_name": "@cswhjiang", "profile_photo": "http://tp1.sinaimg.cn/2358675560/50/5646390744/1", "poster_link": "http://weibo.com/2358675560", "retweet_poster_name": "@\u6708\u8272\u9ec4\u6cc9_StarDuster", "original_link": "http://weibo.com/2358675560/BDAeD4V0T"}, {"img_size": "176,300", "text": "\u3010\u51e0\u4e2aAkka\u6280\u5de7\u3011<a href=\"http://t.cn/RZbGSsI\" target=\"_blank\">http://t.cn/RZbGSsI</a> \u5c3d\u7ba1Scala\u63d0\u4f9b\u5176\u5b83\u51e0\u79cd\u5f3a\u5927\u7684\u5904\u7406\u5e76\u53d1\u8303\u5f0f\uff0c\u4f46\u662f\u4f5c\u8005\u8ba4\u4e3aActor\u662f\u6700\u4e3a\u4f18\u96c5\u7684\u6982\u5ff5\u4e4b\u4e00\uff0c\u5e76\u901a\u8fc7\u51e0\u4e2a\u793a\u4f8b\u6765\u5c55\u793a\u5b83\u7684\u6280\u5de7\uff1aThe cuckoo clock\uff1bBatch processor\uff1bPoor man's back-pressure... \u4e0d\u59a8\u8bd5\u8bd5\u8fd9\u4e2a\u5f3a\u5927\u7684\u5de5\u5177\u3002@2gua @\u4f2f\u4e50\u5934\u6761 @\u767e\u5ea6\u6280\u672f\u6c99\u9f99 @\u597d\u4e1c\u897f\u4f20\u9001\u95e8 ", "poster_name": "@\u7f51\u8def\u51b7\u773c", "profile_photo": "http://tp3.sinaimg.cn/1715118170/50/5653230631/1", "poster_link": "http://weibo.com/1715118170", "post_time": "2015-01-01", "img_url": "http://ww4.sinaimg.cn/large/663aa05ajw1enudw61fsig204w08cgm2.gif", "original_link": "http://weibo.com/1715118170/BDzXaEaXY"}, {"img_size": "717,2850", "text": "\u30102014\u5e74C++\u5e74\u5ea6\u603b\u7ed3\u3011<a href=\"http://t.cn/RZ4YF4y\" target=\"_blank\">http://t.cn/RZ4YF4y</a> \u8fd9\u662fCode And Graphics\u7f51\u7ad9\u5bf92014\u5e74\u7684\u8fdb\u5c55\u72b6\u6001\u8fdb\u884c\u603b\u7ed3\uff0c\u6210\u7ee9\u5355\u4e0d\u9519\u3002\u8f6c\u9700\uff01", "poster_name": "@\u7f51\u8def\u51b7\u773c", "profile_photo": "http://tp3.sinaimg.cn/1715118170/50/5653230631/1", "poster_link": "http://weibo.com/1715118170", "post_time": "2015-01-01", "img_url": "http://ww4.sinaimg.cn/large/663aa05ajw1enudoaztszj20jx2767pk.jpg", "original_link": "http://weibo.com/1715118170/BDzU6E4Bf"}, {"post_time": "2015-01-01", "text": "\u6211\u76842014\u6280\u672f\u6d41\u6c34\u5e10\uff0c\u6ca1\u6709\u5f62\u800c\u4e0a\u7684\u601d\u8003\uff0c\u8bb0\u4e00\u7bc7\u5e73\u6de1\u7684\u6d41\u6c34\u5e10\u3002<a href=\"http://t.cn/RZbJ9oy\" target=\"_blank\">http://t.cn/RZbJ9oy</a>", "poster_name": "@\u6c5f\u5357\u767d\u8863Calvin", "profile_photo": "http://tp3.sinaimg.cn/1728555142/50/5674402979/1", "poster_link": "http://weibo.com/1728555142", "original_link": "http://weibo.com/1728555142/BDzTA8m5z"}, {"post_time": "2015-01-01", "text": "\u53d1\u8868\u4e86\u535a\u6587\u300a\u5927\u6570\u636e\u5206\u6790\u5230\u5e95\u9700\u8981\u591a\u5c11\u79cd\u5de5\u5177\uff1f \u300b<a href=\"http://t.cn/RZbtCs5\" target=\"_blank\">http://t.cn/RZbtCs5</a>", "poster_name": "@\u674e\u822a\u535a\u58eb", "profile_photo": "http://tp3.sinaimg.cn/2060750830/50/5601079555/1", "poster_link": "http://weibo.com/2060750830", "original_link": "http://weibo.com/2060750830/BDzFk4q5a"}, {"post_time": "2015-01-01", "text": "\u3010Linux\u5b89\u5168\u68c0\u67e5\u65b9\u6cd5\u3011 Linux\u5b89\u5168\u68c0\u67e5\u65b9\u6cd5 ... \u8be6\u89c1\uff1a<a href=\"http://t.cn/zjOtOUd\" target=\"_blank\">http://t.cn/zjOtOUd</a>", "poster_name": "@IT\u6280\u672f\u535a\u5ba2\u5927\u5b66\u4e60", "profile_photo": "http://tp1.sinaimg.cn/1646218964/50/1279883225/1", "poster_link": "http://weibo.com/1646218964", "original_link": "http://weibo.com/1646218964/BDzv9t4TT"}, {"post_time": "2015-01-01", "text": "Sentry\u662f\u975e\u5e38\u6d41\u884c(Stars 6k+)\u7684\u5f02\u5e38\u65e5\u5fd7\u6536\u96c6\u5206\u6790\u62a5\u8b66\u7cfb\u7edf\uff0c\u65e0\u987b\u4fee\u6539\u4ee3\u7801\u5c31\u53ef\u4ee5\u6dfb\u52a0\u65e5\u5fd7\u76d1\u63a7\u529f\u80fd\uff0c\u4f46\u662f\u5f88\u96be\u90e8\u7f72\uff0c\u600e\u4e48\u529e @larrycaiyu @\u65e0\u95fbUnknwon <a href=\"http://t.cn/zlQCjOZ\" target=\"_blank\">http://t.cn/zlQCjOZ</a>", "poster_name": "@tobe\u9648\u8fea\u8c6a", "profile_photo": "http://tp3.sinaimg.cn/2622517194/50/22872481252/1", "poster_link": "http://weibo.com/2622517194", "original_link": "http://weibo.com/2622517194/BDzla68uJ"}, {"post_time": "2015-01-01", "text": "laoshandaoshi.so \u914d\u7f6e\u597d\u4e86\uff0c\u9700\u8981\u8c37\u6b4c\u670d\u52a1\u7684\u540c\u5b66\u53ef\u4ee5\u8bbf\u95ee <a href=\"http://t.cn/RZbGlnY\" target=\"_blank\">http://t.cn/RZbGlnY</a> \u770b\u770b\u6548\u679c\u3002\u987a\u4fbf\u63a8\u8350\u4e00\u4e0b vultr.com \u7684vps\u670d\u52a1\uff0cssd\u7684\uff0c\u6027\u4ef7\u6bd4\u975e\u5e38\u9ad8\u3002@github\u7cbe\u9009", "poster_name": "@\u6708\u660e\u6ca7\u6d77", "profile_photo": "http://tp3.sinaimg.cn/1645875054/50/5640171096/1", "poster_link": "http://weibo.com/1645875054", "original_link": "http://weibo.com/1645875054/BDzfBewt0"}, {"img_size": "424,453", "text": "\u3010Nginx\u7f13\u5b58\u89e3\u51b3\u65b9\u6848\uff1aSRCache\u3011 \u524d\u4e9b\u5929\u5e2e\u522b\u4eba\u4f18\u5316PHP\u7a0b\u5e8f\uff0c\u641e\u5f97\u7070\u5934\u571f\u8138\uff0c\u6700\u540e\u9ed4\u9a74\u6280\u7a77\u5f00\u542f\u4e86FastCGI Cache\uff0c\u7b97\u662f\u52c9\u5f3a\u5e94\u4ed8\u8fc7\u53bb\u4e86\u5427\u3002\u4e0d\u8fc7FastCGI Cache\u4e0d\u652f\u6301\u5206\u5e03\u5f0f\u7f13\u5b58\uff0c\u5f53\u670d\u52a1\u5668\u5f88\u591a\u7684\u65f6\u5019\uff0c\u5197\u4f59\u7684\u6d6a... \u8be6\u89c1\uff1a<a href=\"http://t.cn/RzSGmJW\" target=\"_blank\">http://t.cn/RzSGmJW</a>", "poster_name": "@IT\u6280\u672f\u535a\u5ba2\u5927\u5b66\u4e60", "profile_photo": "http://tp1.sinaimg.cn/1646218964/50/1279883225/1", "poster_link": "http://weibo.com/1646218964", "post_time": "2015-01-01", "img_url": "http://ww1.sinaimg.cn/large/621f4ed4jw1enua707z7vj20bs0cljsb.jpg", "original_link": "http://weibo.com/1646218964/BDz7e7NC3"}, {"post_time": "2015-01-01", "text": "\u77e5\u4e4eCTO\u674e\u7533\u7533\uff1a\u4ece0\u5230100\u2014\u2014\u77e5\u4e4e\u67b6\u6784\u53d8\u8fc1\u53f2 <a href=\"http://t.cn/RZ4sSxf\" target=\"_blank\">http://t.cn/RZ4sSxf</a>", "poster_name": "@\u706b\u4e01\u7b14\u8bb0", "profile_photo": "http://tp2.sinaimg.cn/1840408525/50/5710058292/1", "poster_link": "http://weibo.com/1840408525", "original_link": "http://weibo.com/1840408525/BDydxeVKs"}, {"post_time": "2015-01-01", "text": "\u3010Quora\uff1a\u601d\u7ef4\u5bfc\u5411\u7684\u95ee\u7b54\u5e73\u53f0\u3011 Quora\u4e0a\u6709\u4e00\u4e2a\u5f88\u6709\u610f\u601d\u7684\u95ee\u9898\uff1a\u96c5\u864e\u95ee\u7b54\u5dee\u52b2\u5728\u54ea\u4e9b\u5730\u65b9\uff1f\u7528\u6237\u4eec\u7eb7\u7eb7\u8868\u6001\uff0c\u5f52\u7eb3\u8d77\u6765\u6709\u516d\u70b9\uff1a1\u3001\u56de\u7b54\u6beb\u65e0\u8d28\u91cf\uff1b2\u3001\u63d0\u95ee\u6beb\u65e0\u6c34\u5e73\uff1b3\u3001\u65e0\u6cd5\u4fe1\u4efb\u56de\u7b54\u8005\uff1b4\u3001\u54cd\u5e94\u6162\uff1b5\u3001\u8d21\u732e\u6fc0\u52b1\u5c0f\uff1b6\u3001\u754c\u9762\u96be\u770b\u3002 \u4e5f\u5c31... \u8be6\u89c1\uff1a<a href=\"http://t.cn/zH0HhHF\" target=\"_blank\">http://t.cn/zH0HhHF</a>", "poster_name": "@IT\u6280\u672f\u535a\u5ba2\u5927\u5b66\u4e60", "profile_photo": "http://tp1.sinaimg.cn/1646218964/50/1279883225/1", "poster_link": "http://weibo.com/1646218964", "original_link": "http://weibo.com/1646218964/BDxVJB0tQ"}, {"img_size": "1054,792", "text": "\u5206\u6790Redis\u67b6\u6784\u8bbe\u8ba1 - God's blog - \u535a\u5ba2\u9891\u9053 - CSDN.NET <a href=\"http://t.cn/RZ4BcJN\" target=\"_blank\">http://t.cn/RZ4BcJN</a> ", "poster_name": "@\u9ec4\u5065\u5b8f_huangz", "profile_photo": "http://tp1.sinaimg.cn/3219474004/50/40017523747/1", "poster_link": "http://weibo.com/3219474004", "post_time": "2015-01-01", "img_url": "http://ww3.sinaimg.cn/large/bfe54654jw1enu3edbrq8j20ta0m0dkg.jpg", "original_link": "http://weibo.com/3219474004/BDxzO3j7E"}, {"img_size": "347,142", "text": "\u3010Redis\u548cMemcached\u7684\u533a\u522b\u3011 Redis\u652f\u6301\u670d\u52a1\u5668\u7aef\u7684\u6570\u636e\u64cd\u4f5c\uff1aRedis\u76f8\u6bd4Memcached\u6765\u8bf4\uff0c\u62e5\u6709\u66f4\u591a\u7684\u6570\u636e\u7ed3\u6784\u548c\u5e76\u652f\u6301\u66f4\u4e30\u5bcc\u7684\u6570\u636e\u64cd\u4f5c\uff0c\u901a\u5e38\u5728Memcached\u91cc\uff0c\u4f60\u9700\u8981\u5c06\u6570\u636e\u62ff\u5230\u5ba2\u6237\u7aef\u6765\u8fdb\u884c\u7c7b\u4f3c\u7684\u4fee\u6539\u518dse... \u8be6\u89c1\uff1a<a href=\"http://t.cn/RzadzE0\" target=\"_blank\">http://t.cn/RzadzE0</a>", "poster_name": "@IT\u6280\u672f\u535a\u5ba2\u5927\u5b66\u4e60", "profile_photo": "http://tp1.sinaimg.cn/1646218964/50/1279883225/1", "poster_link": "http://weibo.com/1646218964", "post_time": "2015-01-01", "img_url": "http://ww3.sinaimg.cn/large/621f4ed4jw1enu3992vngj209n03ymx7.jpg", "original_link": "http://weibo.com/1646218964/BDxxNmNMm"}, {"img_size": "418,640", "text": "\u5206\u4eab\u56fe\u7247\u5728\u5199\u300a\u6d6a\u6f6e\u4e4b\u5dc5\u300b\u7684\u7eed\u96c6\uff0c\u4ecb\u7ecd\u4f2f\u514b\u5229\u3002\u770b\u770b\u4ec0\u4e48\u662f\u6700\u725b\u7684\u5927\u5b66\uff0c\u53ea\u6709\u8bfa\u8d1d\u5c14\u5956\u83b7\u5f97\u8005\u624d\u6709\u56fa\u5b9a\u7684\u505c\u8f66\u4f4d\u3002\uff08NL \u662f nobel laureates\u7684\u7f29\u5199\uff09\u3002\u4f2f\u514b\u5229\u5730\u5904\u5c71\u57ce\uff0c\u505c\u8f66\u4f4d\u5c11\u3002\u8be5\u6821\u73b0\u5728\u670931\u4f4d\u8bfa\u5956\u83b7\u5f97\u8005\uff0c\u8d85\u8fc7\u7f8e\u3001\u82f1\u3001\u6cd5\u3001\u5fb7\u5916\u4efb\u4f55\u4e00\u4e2a\u56fd\u5bb6\u3002", "poster_name": "@\u5434\u519b\u535a\u58eb", "profile_photo": "http://tp3.sinaimg.cn/2887339314/50/39998666801/1", "poster_link": "http://weibo.com/2887339314", "post_time": "2015-01-01", "img_url": "http://ww2.sinaimg.cn/large/ac194d32jw1enu2xhrrsxj20bm0hs42l.jpg", "original_link": "http://weibo.com/2887339314/BDxua9XWN"}, {"post_time": "2015-01-01", "text": "\u3010\u77ed\u7f51\u5740\u670d\u52a1\u7684\u6784\u5efa\u3011 \u77ed\u7f51\u5740\u670d\u52a1\u8bf4\u767d\u4e86\u5c31\u662fURL\u6620\u5c04\uff0c\u5c06\u8f83\u957f\u7684URL\u6620\u5c04\u6210\u77ed\u5b57\u7b26\u4e32\u3002\u77ed\u5740\u672c\u8d28\u4e0a\u662f\u5b9e\u73b0\u4e86\u4e00\u4e2a\u6620\u5c04\u51fd\u6570 f(x)-> y \u3002\u5bf9\u4e8e\u6bcf\u4e00\u4e2a y, \u80fd\u591f\u627e\u5230\u552f\u4e00\u7684\u4e00\u4e2a x \u4f7f\u5f97 f(x) = y\u3002\u5373\u4e0d\u80fd\u4ea7\u751f\u4e00\u77edURL\u5730\u5740\u5bf9\u5e94... \u8be6\u89c1\uff1a<a href=\"http://t.cn/RzS9GBS\" target=\"_blank\">http://t.cn/RzS9GBS</a>", "poster_name": "@IT\u6280\u672f\u535a\u5ba2\u5927\u5b66\u4e60", "profile_photo": "http://tp1.sinaimg.cn/1646218964/50/1279883225/1", "poster_link": "http://weibo.com/1646218964", "original_link": "http://weibo.com/1646218964/BDwL62ANQ"}, {"post_time": "2015-01-01", "text": "#\u63a8\u8350#\u4ee5\u4e0b\u662f\u51e0\u4f4d\u5206\u4eab\u8d44\u6e90\u7684\u79c1\u535a\uff1a@\u6b21\u5bb6\u795e\u53d7 @\u8bbe\u5b9a\u63a7 @\u4f20\u5a92\u8001\u8ddf\u73ed @\u4e07\u4e8b\u98ce\u8fc7\u8033 @\u8d44\u6e90\u4eba\u9f99\u9aa7 @\u84dd\u5f71\u5c4b @\u732b\u53d4Mack @\u9646\u6d51\u620e @\u597d\u4e1c\u897f\u4f20\u9001\u95e8 @\u6ca1\u6211\u627e\u4e0d\u5230\u7684\u7535\u5b50\u4e66 \u4ed6\u4eec\u4f1a\u5206\u4eab\u4e00\u4e9b\u7535\u5f71\u97f3\u4e50\u4ee5\u53ca\u5b66\u672f\u8d44\u6e90\uff0c\u5982\u679c\u6709\u56f0\u96be\u4e5f\u53ef\u5411\u4ed6\u4eec\u6c42\u52a9\uff0c\u8d76\u7d27\u5173\u6ce8\u8d77\u6765\uff01", "poster_name": "@Even\u53ea\u662f\u4e00\u77ac", "profile_photo": "http://tp4.sinaimg.cn/2460355055/50/40063648033/0", "poster_link": "http://weibo.com/2460355055", "original_link": "http://weibo.com/2460355055/BDwB9yTXW"}, {"img_size": "300,200", "text": "\u3010\u6570\u636e\u5e93\u6027\u80fd\u7684\u4e09\u4e2a\u654c\u4eba\u3011<a href=\"http://t.cn/RZUQiM4\" target=\"_blank\">http://t.cn/RZUQiM4</a> \u968f\u7740\u6570\u636e\u5e93\u6570\u636e\u53d8\u5927\uff0c\u7cfb\u7edf\u6027\u80fd\u5c06\u4f1a\u4e0b\u964d\u3002\u672c\u6587\u8ba9\u4f60\u4e86\u89e3\u6570\u636e\u5e93\u6240\u906d\u9047\u76843\u4e2a\u654c\u4eba\uff1a\u8868\u626b\u63cf\uff1b\u5e76\u53d1\u7ade\u4e89\uff1b\u6162\u5199\uff0c\u907f\u514d\u9677\u5165\u6570\u636e\u6d41\u7ed3\u6210\u7684\u6ce5\u6f6d\uff0c\u4ee5\u7a81\u7834\u6027\u80fd\u74f6\u9888\u3002\u5efa\u8bae\u6536\u85cf\uff01@2gua @\u4f2f\u4e50\u5934\u6761 @\u767e\u5ea6\u6280\u672f\u6c99\u9f99", "poster_name": "@\u7f51\u8def\u51b7\u773c", "profile_photo": "http://tp3.sinaimg.cn/1715118170/50/5653230631/1", "poster_link": "http://weibo.com/1715118170", "post_time": "2015-01-01", "img_url": "http://ww3.sinaimg.cn/large/663aa05agw1entxzq1hd6j208c05kmx3.jpg", "original_link": "http://weibo.com/1715118170/BDwlZCxGl"}, {"post_time": "2015-01-01", "text": "\u3010\u7528\u6237\u53ca\u7528\u6237\u7279\u5f81\u3011 \u8981\u521b\u5efa1\u4e2a\u53ef\u4ee5\u4e0e\u7528\u6237\u6709\u6548\u4ea4\u6d41\u7684\u7f51\u7ad9\uff0c\u5fc5\u987b\u8003\u8651\u5230\u4e0e\u4f60\u4ea4\u6d41\u7684\u7528\u6237\u3002\u7406\u89e3\u7528\u6237\u7684\u9700\u6c42\u5bf9\u6211\u4eec\u51b3\u5b9a\u7f51\u7ad9\u5185\u5bb9\u3001\u4fe1\u606f\u91cf\u3001\u7528\u6237\u4ee5\u53ca\u5185\u5bb9\u7ed3\u6784\u81f3\u5173\u91cd\u8981\u3002\u7528\u6237\u4e0d\u662f\u88ab\u52a8\u7684\u63a5\u53d7\u7f51\u7ad9\u63d0\u4f9b\u7684\u4fe1\u606f\uff0c\u6240\u6709\u4eba\u90fd\u4f1a\u4e0d\u65ad\u7684\u5730\u6839\u636e\u81ea\u8eab\u7ecf\u9a8c\u548c\u731c\u6d4b\u6765\u7406\u89e3\u3002\u81ea... \u8be6\u89c1\uff1a<a href=\"http://t.cn/zYuXJDD\" target=\"_blank\">http://t.cn/zYuXJDD</a>", "poster_name": "@IT\u6280\u672f\u535a\u5ba2\u5927\u5b66\u4e60", "profile_photo": "http://tp1.sinaimg.cn/1646218964/50/1279883225/1", "poster_link": "http://weibo.com/1646218964", "original_link": "http://weibo.com/1646218964/BDvXYoAmG"}, {"post_time": "2015-01-01", "text": "saas\u521b\u4e1a\u5fc5\u8bfb<a href=\"http://t.cn/RZ4KWJr\" target=\"_blank\">http://t.cn/RZ4KWJr</a>", "poster_name": "@\u6613\u5ea6-\u6f58\u4fca\u52c7", "profile_photo": "http://tp4.sinaimg.cn/1843828575/50/5699235853/1", "poster_link": "http://weibo.com/1843828575", "original_link": "http://weibo.com/1843828575/BDvIWpfrm"}, {"post_time": "2015-01-01", "text": "petuum 1.0\u7248\u5df2\u7ecf\u53d1\u5e03\uff0c\u65b0\u589e\u4e86\u4e0d\u5c11\u7b97\u6cd5\u652f\u6301\u3002\u641eparameter server\u7684\u540c\u597d\u53ef\u4ee5\u5173\u6ce8\u4e0b\u3002 <a href=\"http://t.cn/RZ4onlo\" target=\"_blank\">http://t.cn/RZ4onlo</a>", "poster_name": "@\u5b59\u660e\u660e_SmarterChina", "profile_photo": "http://tp3.sinaimg.cn/1914450674/50/5644229416/1", "poster_link": "http://weibo.com/1914450674", "original_link": "http://weibo.com/1914450674/BDvELcQwc"}, {"img_size": "440,8747", "text": "\u3010\u9a6c\u4e91\u90fd\u4e0d\u77e5\u9053\u7684\u963f\u91cc\"\u5927\u6570\u636e\"\u3011\u8fce\u77402015\u5e74\u7684\u7b2c\u4e00\u7f15\u9633\u5149\uff08\u7a97\u5916\u53ea\u6709\u96fe\u973e\u7684\u540c\u5b66\u8bf7\u81ea\u884c\u8111\u8865\uff09\uff0c\u4fdd\u969c\u541b\u7ed9\u5927\u5bb6\u7206\u4e9b\u6599\uff0c\u770b\u770b\u963f\u91cc2014\u5e74\u7684\u90a3\u4e9b\u4eba\u3001\u90a3\u4e9b\u6570", "poster_name": "@\u963f\u91cc\u6280\u672f\u4fdd\u969c", "profile_photo": "http://tp1.sinaimg.cn/3851645388/50/40059402991/1", "poster_link": "http://weibo.com/3851645388", "post_time": "2015-01-01", "img_url": "http://ww1.sinaimg.cn/large/e59371ccgw1ensuxoqm6mj20c86qz7wh.jpg", "original_link": "http://weibo.com/3851645388/BDvgdq7un"}, {"img_size": "600,370", "text": "\u3010\u76d8\u70b92014\uff1a10\u4e2a\u8bcd\u6c47\u91cc\u7684\u79fb\u52a8\u4e92\u8054\u7f51 \u3011\u5168\u6587=><a href=\"http://t.cn/RZ4iLoy\" target=\"_blank\">http://t.cn/RZ4iLoy</a>", "poster_name": "@WEB\u5f00\u53d1\u8005", "profile_photo": "http://tp1.sinaimg.cn/2857596964/50/40064117139/1", "poster_link": "http://weibo.com/2857596964", "post_time": "2015-01-01", "img_url": "http://ww4.sinaimg.cn/large/aa537824jw1entsx86895j20go0aaaax.jpg", "original_link": "http://weibo.com/2857596964/BDvcFABfw"}, {"img_size": "485,320", "text": "\u3010\u4e2d\u56fd\u4e92\u8054\u7f512014\u5927\u4e8b\u8bb0\u3011\u8ba9\u6211\u4eec\u6574\u7406\u4e00\u4e0b\u601d\u7eea\uff0c\u4e00\u8d77\u56de\u987e2014\u4e2d\u56fd\u4e92\u8054\u7f51\u4e0a\u7684\u5927\u4e8b\u8bb0\u3002\u5168\u6587=><a href=\"http://t.cn/RZ4JsUV\" target=\"_blank\">http://t.cn/RZ4JsUV</a>", "poster_name": "@WEB\u5f00\u53d1\u8005", "profile_photo": "http://tp1.sinaimg.cn/2857596964/50/40064117139/1", "poster_link": "http://weibo.com/2857596964", "post_time": "2015-01-01", "img_url": "http://ww1.sinaimg.cn/large/aa537824jw1entsv0jec0j20dh08w0t9.jpg", "original_link": "http://weibo.com/2857596964/BDvbOoRQi"}, {"img_size": "650,390", "text": "\u3010HQueue\uff1a\u57fa\u4e8eHBase\u7684\u6d88\u606f\u961f\u5217\u3011 HQueue\u662f\u4e00\u6dd8\u641c\u7d22\u7f51\u9875\u6293\u53d6\u79bb\u7ebf\u7cfb\u7edf\u56e2\u961f\u57fa\u4e8eHBase\u5f00\u53d1\u7684\u4e00\u5957\u5206\u5e03\u5f0f\u3001\u6301\u4e45\u5316\u6d88\u606f\u961f\u5217\u3002\u5b83\u5229\u7528HTable\u5b58\u50a8\u6d88\u606f\u6570\u636e\uff0c\u501f\u52a9HBase Coprocessor\u5c06\u539f\u59cb\u7684KeyValue\u6570... \u8be6\u89c1\uff1a<a href=\"http://t.cn/RzSnrBq\" target=\"_blank\">http://t.cn/RzSnrBq</a>", "poster_name": "@IT\u6280\u672f\u535a\u5ba2\u5927\u5b66\u4e60", "profile_photo": "http://tp1.sinaimg.cn/1646218964/50/1279883225/1", "poster_link": "http://weibo.com/1646218964", "post_time": "2015-01-01", "img_url": "http://ww4.sinaimg.cn/large/621f4ed4jw1entsuo3fg5j20i20aujuj.jpg", "original_link": "http://weibo.com/1646218964/BDvbFgyDn"}, {"post_time": "2015-01-01", "text": "Web\u6280\u672f\u65e5\u62a5 2014-12-31 <a href=\"http://t.cn/RZ4foi5\" target=\"_blank\">http://t.cn/RZ4foi5</a> 1) AngularJS vs. Backbone.js vs. Ember.js 2) \u6784\u5efaC1000K\u7684\u670d\u52a1\u5668 3) \u514d\u8d39\u5f00\u53d1\u8bfe\u7a0b\u300aHTML5\u79bb\u7ebf\u5e94\u7528\u5b9e\u6218\u6f14\u7ec3\u300b 4) \u4ece0\u5230100\u2014\u2014\u77e5\u4e4e\u67b6\u6784\u53d8\u8fc1\u53f2 5) \u7ef4\u57fa\u767e\u79d1\u5c06\u6240\u6709\u670d\u52a1\u5668\u7684PHP\u5f15\u64ce\u53d8\u4e3aHHVM \u53ef\u70b9\u51fb\u52a0\u957f\u724852\u6761 <a href=\"http://t.cn/RZ4f9LX\" target=\"_blank\">http://t.cn/RZ4f9LX</a>", "poster_name": "@\u597d\u4e1c\u897f\u4f20\u9001\u95e8", "profile_photo": "http://tp1.sinaimg.cn/5220650532/50/5701668539/1", "poster_link": "http://weibo.com/5220650532", "original_link": "http://weibo.com/5220650532/BDuQMFvE5"}, {"post_time": "2015-01-01", "text": "Python\u65e5\u62a5 2014-12-31 <a href=\"http://t.cn/RZ4GMbX\" target=\"_blank\">http://t.cn/RZ4GMbX</a> 1) Lamson\uff1aPython SMTP\u5e94\u7528\u670d\u52a1\u5668 2) Python\u4e2d\u7684\u9ad8\u7ea7\u6570\u636e\u7ed3\u6784 3) Vim\u521d\u63a2 \u6253\u9020Python IDE 4) python \u53d8\u91cf\u547d\u540d\u89c4\u8303 5) \u4f7f\u7528jieba+whoosh\u5b9e\u73b0\u5168\u6587\u641c\u7d22 \u53ef\u70b9\u51fb\u52a0\u957f\u724826\u6761 <a href=\"http://t.cn/RZ4GxBP\" target=\"_blank\">http://t.cn/RZ4GxBP</a>", "poster_name": "@\u597d\u4e1c\u897f\u4f20\u9001\u95e8", "profile_photo": "http://tp1.sinaimg.cn/5220650532/50/5701668539/1", "poster_link": "http://weibo.com/5220650532", "original_link": "http://weibo.com/5220650532/BDujZoj1g"}, {"post_time": "2015-01-01", "text": "\u673a\u5668\u5b66\u4e60\u65e5\u62a5 2014-12-31 <a href=\"http://t.cn/RZ4y6np\" target=\"_blank\">http://t.cn/RZ4y6np</a> 1) \u73bb\u68ee\u6570\u636e\u7684\u547d\u540d\u5b9e\u4f53\u6570\u636e\uff0c\u60c5\u611f\u8bcd\u5178 2) \u5bf9\u5173\u8054\u6570\u636e\u7684\u770b\u6cd5 3) Stochastic Gradient Boosting\u8bad\u7ec3\u8c03\u53c2 4) \u7528GraphLab Create\u5feb\u901f\u4f53\u9a8c\u6df1\u5ea6\u5b66\u4e60 5) \u4eceVariance\u8bf4\u8d77\uff1a\u56de\u5f52\u3001\u805a\u7c7b\u3001\u6b8b\u5dee\u548c\u65b9\u5dee \u53ef\u70b9\u51fb\u52a0\u957f\u724837\u6761 <a href=\"http://t.cn/RZ4y9yI\" target=\"_blank\">http://t.cn/RZ4y9yI</a>", "poster_name": "@\u597d\u4e1c\u897f\u4f20\u9001\u95e8", "profile_photo": "http://tp1.sinaimg.cn/5220650532/50/5701668539/1", "poster_link": "http://weibo.com/5220650532", "original_link": "http://weibo.com/5220650532/BDtTso5tn"}, {"img_size": "750,325", "text": "Mkdocs\u662fdocker\u6587\u6863\u4e2d\u5fc3\u4f7f\u7528\u7684\u6784\u5efa\u5de5\u5177\uff0c\u4f7f\u7528Mkdocs\u53ef\u4ee5\u8f7b\u6613\u5730\u4e3a\u4f60\u7684\u9879\u76ee\u6dfb\u52a0\u5b98\u65b9\u7f51\u7ad9 <a href=\"http://t.cn/RvdqY6t\" target=\"_blank\">http://t.cn/RvdqY6t</a> Dockerfile\u8054\u76df\u4e3a\u6b64\u5b9e\u73b0\u4e86mkdocs-server\u5bb9\u5668\uff0c\u6ca1\u6709\u4efb\u4f55\u4f9d\u8d56\u8fd0\u884cmkdocs\u7f51\u7ad9\uff0c\u7ec8\u4e8e\u5f97\u5230\u5176\u4f5c\u8005Tom Christie\u7684\u8ba4\u53ef\u5566 <a href=\"http://t.cn/RZUBGVx\" target=\"_blank\">http://t.cn/RZUBGVx</a>", "poster_name": "@tobe\u9648\u8fea\u8c6a", "profile_photo": "http://tp3.sinaimg.cn/2622517194/50/22872481252/1", "poster_link": "http://weibo.com/2622517194", "post_time": "2015-01-01", "img_url": "http://ww1.sinaimg.cn/large/9c506fcajw1entbgjoj8dj20ku0910to.jpg", "original_link": "http://weibo.com/2622517194/BDrfqsEsM"}, {"img_size": "768,1024", "text": "\u673a\u5668\u5b66\u4e60\u5b97\u5e08Michael Jordan\u66fe\u8bf4\u641e\u8ba1\u7b97\u673a\u7684\u8981\u591a\u5411\u6570\u5b66\u3001\u7edf\u8ba1\u5b66\u4e60\u3002\u4ed6\u63a8\u8350\u7684\u673a\u5668\u5b66\u4e60\u4e66\u679c\u7136\u90fd\u662f\u5f88\u6570\u5b66\u5f88\u7edf\u8ba1\u7684\uff1a<a href=\"http://t.cn/RZU1vOb\" target=\"_blank\">http://t.cn/RZU1vOb</a> @\u6781\u5ba2\u5934\u6761 \u6211\u548c @\u6b66\u536b\u4e1c \u5f53\u5e74\u5728\u56fe\u7075\u548c\u534e\u7ae0\u51fa\u7684\u6570\u5b66\u7edf\u8ba1\u4e66\u770b\u6765\u53c8\u53ef\u4ee5\u91cd\u5370\u5566\u3002", "poster_name": "@\u5218\u6c5f\u603b\u7f16", "profile_photo": "http://tp1.sinaimg.cn/1642316384/50/5651361487/1", "poster_link": "http://weibo.com/1642316384", "post_time": "2015-01-01", "img_url": "http://ww2.sinaimg.cn/large/61e3c260jw1entb2m13w0j20lc0sgdmm.jpg", "original_link": "http://weibo.com/1642316384/BDranwOP3"}, {"img_size": "458,600", "text": "Genes to Cells \u8868\u7eb8\u5199\u771f | \u65e5\u672c\u5206\u5b50\u751f\u7269\u5b66\u4f1a\u6742\u5fd7\u5c01\u9762\u8d4f .", "poster_name": "@\u65e5\u85dd\u793e", "profile_photo": "http://tp2.sinaimg.cn/2950263733/50/40051824928/0", "poster_link": "http://weibo.com/2950263733", "post_time": "2014-12-31", "img_url": "http://ww2.sinaimg.cn/large/afd973b5jw1entaxrybsvj20cq0gon1n.jpg", "original_link": "http://weibo.com/2950263733/BDr88ozCo"}, {"img_size": "382,11582", "text": "\u3010\u73cd\u60dc\u773c\u524d\u4eba\u3011\u6885\u8273\u82b3\u5728\u544a\u522b\u6f14\u5531\u4f1a\u4e0a\uff0c\u7a7f\u4e0a\u5a5a\u7eb1\uff0c\u8eab\u8fb9\u6ca1\u6709\u65b0\u90ce\uff0c\u5979\u4e3a\u81ea\u5df1\u6380\u8d77\u5934\u7eb1\uff0c\u8bf4\u51fa\u4e86\u8fd9\u6bb5\u53d1\u81ea\u80ba\u8151\u7684\u8bdd\u3002\u5979\u8bf4\u8fd9\u8f88\u5b50\u6700\u5927\u7684\u9057\u61be\u4fbf\u662f\u6ca1\u6709\u4e00\u573a\u5c5e\u4e8e\u81ea\u5df1\u7684\u5a5a\u793c\uff0c\u4e16\u4e8b\u96be\u6599\uff0c\u8bf7\u5728\u62cd\u62d6\u7684\u5973\u751f\u4eec\uff0c\u73cd\u60dc\u773c\u524d\u4eba\uff0c\u628a\u63e1\u5e78\u798f\u3002\u6f14\u5531\u4f1a\u7ed3\u675f\u540e45\u5929\uff0c\u4e5f\u5c31\u662f2003\u5e74\u768412\u670830\u53f7\uff0c\u6885\u8273\u82b3\u75c5\u901d\uff0c\u7ec8\u5e7440\u5c81\u3002(@\u601d\u60f3\u805a\u7126)", "poster_name": "@\u65b0\u6d6a\u6e56\u5317", "profile_photo": "http://tp1.sinaimg.cn/2049389352/50/5710058725/0", "poster_link": "http://weibo.com/2049389352", "post_time": "2014-12-31", "img_url": "http://ww2.sinaimg.cn/large/7a273328jw1ent9bqvgfuj20am8xqqnu.jpg", "original_link": "http://weibo.com/2049389352/BDqLs937c"}, {"img_size": "553,312", "text": "\u522b\u5c0f\u770b\u6811\u8393\u6d3e \u6781\u5ba2\u4eec\u73a9\u51fa16\u4e2a\u500d\u513f\u6709\u8da3\u7684\u9879\u76ee <a href=\"http://t.cn/RZUw8T1\" target=\"_blank\">http://t.cn/RZUw8T1</a> ", "poster_name": "@DataMooc", "profile_photo": "http://tp4.sinaimg.cn/1649885883/50/5656984412/1", "poster_link": "http://weibo.com/1649885883", "post_time": "2014-12-31", "img_url": "http://ww1.sinaimg.cn/large/625742bbjw1ent6opb5hdj20fd08oaai.jpg", "original_link": "http://weibo.com/1649885883/BDqantS4m"}, {"post_time": "2014-12-31", "text": "\u3010\u4ea7\u54c1\u7ecf\u7406\u80fd\u529b\u6a21\u578b\u89e3\u8bf4-\u5b66\u4e60\u3011 5\u5e74\u4ea7\u54c1\u7ecf\u7406\u5b66\u4e60\u6210\u957f\u8def\u56de\u5fc6\uff1a \u56de\u987e\u901d\u53bb\u76845\u5e74\u4ea7\u54c1\u804c\u4e1a\u751f\u6daf\uff0c\u53d1\u73b0\u81ea\u5df1\u5b66\u4e60\u6210\u957f\u7684\u9053\u8def\u4e0a\uff0c\u8fd8\u662f\u66f2\u66f2\u6298\u6298\uff0c\u4e5f\u4e0d\u77e5\u9053\u600e\u4e48\u7740\u5c31\u8d70\u5230\u4e86\u773c\u524d\u3002\u5199\u6b64\u7bc7\u548c\u5e7f\u5927\u5b66\u4e60\u9053\u8def\u4e0a\u7684PM\u4eec\u4e00\u8d77\u5206\u4eab\u5427\uff0c\u5e0c\u671b\u5bf9\u4f60\u4eec\u6709\u6240\u542f\u53d1\u548c\u5e2e\u52a9\u3002 0... \u8be6\u89c1\uff1a<a href=\"http://t.cn/zYcUYLl\" target=\"_blank\">http://t.cn/zYcUYLl</a>", "poster_name": "@IT\u6280\u672f\u535a\u5ba2\u5927\u5b66\u4e60", "profile_photo": "http://tp1.sinaimg.cn/1646218964/50/1279883225/1", "poster_link": "http://weibo.com/1646218964", "original_link": "http://weibo.com/1646218964/BDq4GoD6m"}, {"post_time": "2014-12-31", "text": "\u3010\u6df1\u5ea6\u5b66\u4e60\u7b97\u6cd5\u7684\u51e0\u4e2a\u96be\u70b9\u3011<a href=\"http://t.cn/RZUAuOG\" target=\"_blank\">http://t.cn/RZUAuOG</a> \u4e00\u4e2a\u4ec1\u8005\u89c1\u4ec1\u667a\u8005\u89c1\u667a\u7684\u95ee\u9898\uff0c\u4f5c\u8005\u8ba4\u4e3a\u7684\u96be\u70b9\u4e3a\uff1a1\u3001\u5c40\u90e8\u6700\u4f18\u95ee\u9898\u30022\u3001\u5185\u5b58\u6d88\u8017\u5de8\u5927\uff0c\u8ba1\u7b97\u590d\u6742\u30023\u3001\u4eba\u8111\u673a\u7406\u8fd8\u6709\u5f88\u591a\u6ca1\u7528\u4e0a\u30024\u3001\u4eba\u4e3a\u8bbe\u8ba1\u6a21\u7248\u7684\u53ef\u884c\u6027\u30025\u3001\u4ee3\u4ef7\u51fd\u6570\u7684\u8bbe\u8ba1\u65b9\u6cd5\u30026\u3001\u6574\u4e2a\u795e\u7ecf\u7f51\u7edc\u7cfb\u7edf\u7684\u8bbe\u8ba1\u3002", "poster_name": "@\u6211\u7231\u673a\u5668\u5b66\u4e60", "profile_photo": "http://tp2.sinaimg.cn/5066241201/50/5690591470/1", "poster_link": "http://weibo.com/5066241201", "original_link": "http://weibo.com/5066241201/BDq2lzOUh"}, {"post_time": "2014-12-31", "text": "\u3010\u6784\u5efaC1000K\u7684\u670d\u52a1\u5668(1) \u2013 \u57fa\u7840\u3011 \u73b0\u5728, \u8be5\u662f\u8003\u8651 C1000K, \u4e5f\u5c31\u662f\u767e\u4e07\u8fde\u63a5\u7684\u95ee\u9898\u7684\u65f6\u5019\u4e86. \u50cf Twitter, weibo, Facebook \u8fd9\u4e9b\u7f51\u7ad9, \u5b83\u4eec\u7684\u540c\u65f6\u5728\u7ebf\u7528\u6237\u6709\u4e0a\u5343\u4e07, \u540c\u65f6\u53c8\u5e0c\u671b\u6d88\u606f\u80fd\u63a5\u8fd1\u5b9e... \u8be6\u89c1\uff1a<a href=\"http://t.cn/RzaBExl\" target=\"_blank\">http://t.cn/RzaBExl</a>", "poster_name": "@IT\u6280\u672f\u535a\u5ba2\u5927\u5b66\u4e60", "profile_photo": "http://tp1.sinaimg.cn/1646218964/50/1279883225/1", "poster_link": "http://weibo.com/1646218964", "original_link": "http://weibo.com/1646218964/BDpGI4qUC"}, {"img_size": "234,197", "text": "\u201c@zhujiang73\uff1a\u4eceK\u8fd1\u90bb\u7b97\u6cd5\u3001\u8ddd\u79bb\u5ea6\u91cf\u8c08\u5230KD\u6811\u3001SIFT+BBF\u7b97\u6cd5 - \u7ed3\u6784\u4e4b\u6cd5 \u7b97\u6cd5\u4e4b\u9053 - \u535a\u5ba2\u9891\u9053 - CSDN.NET <a href=\"http://t.cn/RZUw4YH\" target=\"_blank\">http://t.cn/RZUw4YH</a>\u201d  \u2014\u2014\u5206\u4eab\u81ea\u7b80\u00b7\u8bfb(<a href=\"http://t.cn/RP0wWxB\" target=\"_blank\">http://t.cn/RP0wWxB</a> ),\u7ad9\u5728\u5de8\u4eba\u80a9\u4e0a\u770b\u5fae\u535a\u3002 <a href=\"http://t.cn/RZUa7gy\" target=\"_blank\">http://t.cn/RZUa7gy</a> ", "poster_name": "@\u7231\u53ef\u53ef-\u7231\u751f\u6d3b", "profile_photo": "http://tp2.sinaimg.cn/1402400261/50/5713579194/1", "poster_link": "http://weibo.com/1402400261", "post_time": "2014-12-31", "img_url": "http://ww2.sinaimg.cn/large/5396ee05jw1ent2ahrlz5j206i05h3yj.jpg", "original_link": "http://weibo.com/1402400261/BDpaFa474"}, {"retweet_text": "\u7ee7\u7eed\u8bf7\u6559\u5404\u4f4d\u725b\u4eba\uff1a\u73b0\u6709\u4e00\u4e2a\u95ee\u9898\uff1a\u8981\u83b7\u5f97\u4e00\u7cfb\u5217\u53e5\u5b50\u7684\u6392\u5e8f\uff0c\u8f93\u5165\u662f\u4e24\u4e24\u6bd4\u8f83\uff0c\u6bd4\u5982\u8bf4a>b, a>c, c>b\uff0c\u73b0\u5728\u4ece\u8fd9\u4e9bpartial order\u5b66\u4e60\u4e00\u4e2atotal order\uff0c\u5e76\u9884\u6d4b\u672a\u6765\u8f93\u5165\u7684\u6392\u5e8f\u3002\u8fd9\u6709\u6ca1\u6709\u73b0\u6210\u7684\u5de5\u5177\u53ef\u4ee5\u7528\uff1f\u5982\u679c\u6ca1\u6709\uff0c\u662f\u4e0d\u662f\u67d0\u79cdlearn to rank\u7b97\u6cd5\u53ef\u4ee5\u7528\uff1f\u6216\u8005\u5176\u4ed6\u66f4\u7b80\u5355\u7684\u65b9\u6cd5\uff1f", "post_time": "2014-12-31", "retweet_poster_link": "http://weibo.com/1932835417", "text": "LTR\u7684Python\u5de5\u5177\u5305 //@\u897f\u74dc\u5927\u4e38\u5b50\u6c64: \u611f\u8c22\u5404\u4f4d\u6307\u70b9\uff0c\u8bd5\u4e86Python\u4e0b\u76845\u4e2aLTR\u5b9e\u73b0\u6216\u8005binding\uff1ascikit-learn LinearSVC\uff0cSVMRank\uff0cRankLib\uff0cmltool\uff0cRankSVM \u94fe\u63a5\u603b\u7ed3\u5728\u8fd9\u91cc <a href=\"http://t.cn/RZUXbpi\" target=\"_blank\">http://t.cn/RZUXbpi</a>", "poster_name": "@\u597d\u4e1c\u897f\u4f20\u9001\u95e8", "profile_photo": "http://tp1.sinaimg.cn/5220650532/50/5701668539/1", "poster_link": "http://weibo.com/5220650532", "retweet_poster_name": "@\u897f\u74dc\u5927\u4e38\u5b50\u6c64", "original_link": "http://weibo.com/5220650532/BDp6HAG2q"}, {"img_size": "440,4356", "text": "2014\u5e74\u6700\u5371\u9669\u7684\u4e94\u5927\u8f6f\u4ef6\u6f0f\u6d1e<a href=\"http://t.cn/RZ2sxzH\" target=\"_blank\">http://t.cn/RZ2sxzH</a>", "poster_name": "@\u767e\u5ea6\u6280\u672f\u6c99\u9f99", "profile_photo": "http://tp3.sinaimg.cn/1937725874/50/5704096036/1", "poster_link": "http://weibo.com/1937725874", "post_time": "2014-12-31", "img_url": "http://ww3.sinaimg.cn/large/737f59b2jw1enszxrjkngj20c83d0aym.jpg", "original_link": "http://weibo.com/1937725874/BDoDFbeoX"}, {"img_size": "877,552", "text": "\u3010Spark 1.2\uff1a\u5411MapReduce\u5728Hadoop\u4e2d\u7684\u7edf\u6cbb\u5730\u4f4d\u53d1\u8d77\u6311\u6218\u3011\u4f5c\u4e3a\u9762\u5411Hadoop\u5185\u5b58\u5185\u517c\u5b9e\u65f6\u6570\u636e\u5904\u7406\u6846\u67b6\uff0cSpark\u5df2\u7ecf\u57281.0\u7248\u672c\u6b63\u5f0f\u63a8\u51fa\u4e4b\u540e\u9010\u6b65\u8fc8\u4e0a\u53d1\u5c55\u6b63\u8f68\u3002\u7279\u6027\u53d8\u66f4\u8bc1\u660e\u4e86Spark\u5e76\u4e0d\u6ee1\u8db3\u4e8e\u5bf9\u73b0\u6709\u6210\u7ee9\u6539\u8fdb\uff0c\u540c\u65f6\u4e5f\u81f4\u529b\u4e8e\u53d1\u5c55\u6210\u4e00\u6b3e\u8db3\u4ee5\u5e94\u5bf9Hadoop\u73af\u5883\u4e0b\u5927\u89c4\u6a21\u6570\u636e\u5904\u7406\u573a\u666f\u7684\u672a\u6765\u6846\u67b6<a href=\"http://t.cn/RZyn7Ts\" target=\"_blank\">http://t.cn/RZyn7Ts</a>", "poster_name": "@\u4e2d\u56fd\u4e91\u8ba1\u7b97\u8bba\u575b", "profile_photo": "http://tp1.sinaimg.cn/2841727664/50/39996608459/1", "poster_link": "http://weibo.com/2841727664", "post_time": "2014-12-31", "img_url": "http://ww4.sinaimg.cn/large/a96152b0jw1ensoyuto9aj20od0fc0vk.jpg", "original_link": "http://weibo.com/2841727664/BDoDrxvYg"}, {"post_time": "2014-12-31", "text": "\u514d\u8d39\u8bfe\u7a0b\u4e4b\u79fb\u52a8\u5f00\u53d1\u3010IOS\u7bc7\u3011\uff1a\u300a\u5f81\u6218Objective-C\u300b<a href=\"http://t.cn/RZUtiHE\" target=\"_blank\">http://t.cn/RZUtiHE</a>\u300a\u4f7f\u7528Swift\u5f00\u53d1iOS8 App\u5b9e\u6218\u300b<a href=\"http://t.cn/RZUtiHR\" target=\"_blank\">http://t.cn/RZUtiHR</a>\u300aSwift Weather APP\u300b<a href=\"http://t.cn/RZUtiH8\" target=\"_blank\">http://t.cn/RZUtiH8</a>\u300a\u4e00\u8d77\u6765\u505a\u4ef7\u503c\u767e\u4e07\u7684Apple Watch App\uff1a\u5206\u6b67\u7ec8\u7aef\u673a\u300b<a href=\"http://t.cn/RZUtiH3\" target=\"_blank\">http://t.cn/RZUtiH3</a>", "poster_name": "@\u767e\u5ea6\u6280\u672f\u6c99\u9f99", "profile_photo": "http://tp3.sinaimg.cn/1937725874/50/5704096036/1", "poster_link": "http://weibo.com/1937725874", "original_link": "http://weibo.com/1937725874/BDohtmANG"}, {"post_time": "2014-12-31", "text": "\u514d\u8d39\u8bfe\u7a0b\u4e4b\u79fb\u52a8\u5f00\u53d1\u3010Android\u7bc7\u3011\uff1a\u300aAndroid\u4e2d\u5e38\u7528\u9ad8\u7ea7\u63a7\u4ef6\u8be6\u89e3\u6c47\u603b\u300b<a href=\"http://t.cn/RZUtt3c\" target=\"_blank\">http://t.cn/RZUtt3c</a>\u300aAndroid\u4e2d\u7684\u6d88\u606f\u63d0\u793a\u3001\u83dc\u5355\u4e0e\u52a8\u753b\u300b<a href=\"http://t.cn/RZUtt3t\" target=\"_blank\">http://t.cn/RZUtt3t</a>\u300aAndroid\u4e2d\u7684\u6570\u636e\u5b58\u50a8\u3001\u7ec4\u4ef6\u4e0e\u624b\u52bf\u300b<a href=\"http://t.cn/RZUtt35\" target=\"_blank\">http://t.cn/RZUtt35</a>", "poster_name": "@\u767e\u5ea6\u6280\u672f\u6c99\u9f99", "profile_photo": "http://tp3.sinaimg.cn/1937725874/50/5704096036/1", "poster_link": "http://weibo.com/1937725874", "original_link": "http://weibo.com/1937725874/BDogNEDDg"}, {"post_time": "2014-12-31", "text": "\u514d\u8d39\u5f00\u53d1\u8bfe\u7a0b\u4e4b\u524d\u7aef\u5f00\u53d1\uff1a\u300aHTML5\u79bb\u7ebf\u5e94\u7528\u5b9e\u6218\u6f14\u7ec3\u300b<a href=\"http://t.cn/RZUqg5Z\" target=\"_blank\">http://t.cn/RZUqg5Z</a> \u300aJavaScript\u8fdb\u9636\u7bc7\u300b<a href=\"http://t.cn/RZUqg5h\" target=\"_blank\">http://t.cn/RZUqg5h</a> \u300ajQuery\u6e90\u7801\u89e3\u6790\uff08\u67b6\u6784\u4e0e\u4f9d\u8d56\u6a21\u5757\uff09\u300b<a href=\"http://t.cn/RZUqg5z\" target=\"_blank\">http://t.cn/RZUqg5z</a> \u300a\u7535\u5546\u7f51\u7ad9\u524d\u7aef\u67b6\u6784\u300b<a href=\"http://t.cn/RZUqg5x\" target=\"_blank\">http://t.cn/RZUqg5x</a> \u300a\u624b\u628a\u624b\u6559\u4f60\u5b9e\u73b0\u7535\u5546\u7f51\u7ad9\u5f00\u53d1\u300b<a href=\"http://t.cn/RZUqg5X\" target=\"_blank\">http://t.cn/RZUqg5X</a>", "poster_name": "@\u767e\u5ea6\u6280\u672f\u6c99\u9f99", "profile_photo": "http://tp3.sinaimg.cn/1937725874/50/5704096036/1", "poster_link": "http://weibo.com/1937725874", "original_link": "http://weibo.com/1937725874/BDo9K450r"}, {"img_size": "800,1200", "text": "\u6765\u81ea#\u56fe\u866b\u6444\u5f71\u5e08#\uff1a@_\u9ec4\u6e0a_   \u4e1c\u4e09\u73af\u7684\u591c <a href=\"http://t.cn/RZPxxaF\" target=\"_blank\">http://t.cn/RZPxxaF</a>", "poster_name": "@\u56fe\u866b\u6444\u5f71\u7f51", "profile_photo": "http://tp2.sinaimg.cn/1674175865/50/5649682340/1", "poster_link": "http://weibo.com/1674175865", "post_time": "2014-12-31", "img_url": "http://ww3.sinaimg.cn/large/68e4ee61jw1eno6nlr6g7j20m80xcdkq.jpg", "original_link": "http://weibo.com/1674175865/BDnVcdwbD"}, {"img_size": "674,504", "text": "\u5927\u5bb6\u671f\u5f85\u5df2\u4e45\u7684\u201c\u5fae\u535a\u67b6\u6784\u90a3\u4e9b\u4e8b\u513f\u201d\u7684PPT\u6765\u5566~[\u62cd\u624b]\u5fae\u535aV1\u5230V6\uff0c\u5fae\u535a\u7684\u6280\u672f\u67b6\u6784\u90fd\u53d1\u751f\u4e86\u54ea\u4e9b\u53d8\u5316\uff1f\u5de5\u7a0b\u5e08\u4eec\u90fd\u505a\u4e86\u4e9b\u4ec0\u4e48\u5462\uff1f[\u63a8\u8350]\u6233\u53f3\u8fb9\u4e0b\u8f7d[\u6700\u53f3]\uff1a<a href=\"http://t.cn/RZUhkhH\" target=\"_blank\">http://t.cn/RZUhkhH</a>", "poster_name": "@\u5fae\u535a\u7528\u6237\u4ea7\u54c1\u7814\u53d1\u56e2\u961f", "profile_photo": "http://tp4.sinaimg.cn/3272834507/50/5710060561/0", "poster_link": "http://weibo.com/3272834507", "post_time": "2014-12-31", "img_url": "http://ww1.sinaimg.cn/large/c3137dcbjw1ensw1sxjb3j20iq0e0taj.jpg", "original_link": "http://weibo.com/3272834507/BDnPW0GdV"}, {"retweet_text": "\uff3b\u5b59\u949f\u79c0 \u3002\u300a\u64cd\u4f5c\u7cfb\u7edf\u6559\u7a0b\u300b \u3002\u6ce8\u91ca\uff3d\uff08\u5168\uff09\uff081-8\u7ae0\uff09\u3002\u5386\u7ecf\u4e00\u5e74\uff0c\u7ec8\u4e8e\u5b8c\u6210\u3002\u6df1\u611f\u81ea\u5df1\u624d\u758f\u5b66\u6d45\uff0c\u65e0\u6cd5\u80dc\u4efb\u3002\u5e0c\u671b\u8fd9\u4e2a\u6ce8\uff0c\u80fd\u800c\u4e14\u53ea\u8981\u80fd\u5e2e\u52a9\u5230\u4e00\u4e2a\u5e74\u8f7b\u4eba\u3002\u6211\u7684\u5de5\u4f5c\u5c31\u662f\u6709\u4ef7\u503c\u7684\u3002\u795d\u798f\u6211\u4eec\u76842015. \u795d\u798f\u4e2d\u56fd\u3002PDF\u4e0b\u8f7d URL\uff1a1. \u65b0\u6d6avdisk\uff1a<a href=\"http://t.cn/RZyBgZP\" target=\"_blank\">http://t.cn/RZyBgZP</a> \u6216\u8005 2. \u5f2f\u66f2\u8bc4\u8bba\uff1a<a href=\"http://t.cn/RZyBgvL\" target=\"_blank\">http://t.cn/RZyBgvL</a>", "retweet_img_size": "404,489", "post_time": "2014-12-31", "retweet_poster_link": "http://weibo.com/1645518723", "retweet_img_url": "http://ww1.sinaimg.cn/large/62149f83jw1ensq87dzvgj20b80dldg2.jpg", "text": "\u5b59\u949f\u79c0\u300a\u64cd\u4f5c\u7cfb\u7edf\u6559\u7a0b\u300b \u6ce8\u91ca \u3002\u5f3a\u70c8\u63a8\u8350", "poster_name": "@\u597d\u4e1c\u897f\u4f20\u9001\u95e8", "profile_photo": "http://tp1.sinaimg.cn/5220650532/50/5701668539/1", "poster_link": "http://weibo.com/5220650532", "retweet_poster_name": "@\u6e7e\u533a\u8bc4\u8bba", "original_link": "http://weibo.com/5220650532/BDnEmxLTe"}, {"post_time": "2014-12-31", "text": "\u300a\u6211\u5bf9\u5173\u8054\u6570\u636e\u7684\u770b\u6cd5\u300b\u52a0\u4e86\u7b2c\u4e09\u90e8\u5206 <a href=\"http://t.cn/RZygimd\" target=\"_blank\">http://t.cn/RZygimd</a> \u628a\u6570\u636e\u4ece\u539f\u59cb\u7684\u5f62\u5f0f\uff0c\u6bd4\u5982\u65e5\u5fd7\uff0c\u6570\u636e\u5e93\u6216\u6587\u672c\uff0c\u53d8\u6210\u66f4\u9ad8\u8d28\u91cf\u7684\u5f62\u5f0f\uff0c\u6bd4\u5982URI\uff0c\u5173\u7cfb\uff0c\u77e5\u8bc6\u56fe\u8c31\u76f4\u81f3\u672c\u4f53\uff0c\u4e0d\u662f\u4e00\u4e2a\u9ed1\u767d\u8fc7\u7a0b\uff0c\u800c\u662f\u4e00\u4e2a\u4e00\u6b65\u6b65\u6309\u5b9e\u9645\u5de5\u7a0b\u9700\u8981\u6765\u64cd\u4f5c\u7684\u8fc7\u7a0b\u3002\u8001\u8bdd\u8bf4\u9884\u5148\u4f18\u5316\u662f\u4e07\u6076\u4e4b\u6e90\uff0c\u5728\u77e5\u8bc6\u5de5\u7a0b\u4e5f\u662f\u8fd9\u6837\u3002", "poster_name": "@\u897f\u74dc\u5927\u4e38\u5b50\u6c64", "profile_photo": "http://tp2.sinaimg.cn/1932835417/50/5714878873/1", "poster_link": "http://weibo.com/1932835417", "original_link": "http://weibo.com/1932835417/BDmEc8hlj"}, {"img_size": "404,489", "text": "\uff3b\u5b59\u949f\u79c0 \u3002\u300a\u64cd\u4f5c\u7cfb\u7edf\u6559\u7a0b\u300b \u3002\u6ce8\u91ca\uff3d\uff08\u5168\uff09\uff081-8\u7ae0\uff09\u3002\u5386\u7ecf\u4e00\u5e74\uff0c\u7ec8\u4e8e\u5b8c\u6210\u3002\u6df1\u611f\u81ea\u5df1\u624d\u758f\u5b66\u6d45\uff0c\u65e0\u6cd5\u80dc\u4efb\u3002\u5e0c\u671b\u8fd9\u4e2a\u6ce8\uff0c\u80fd\u800c\u4e14\u53ea\u8981\u80fd\u5e2e\u52a9\u5230\u4e00\u4e2a\u5e74\u8f7b\u4eba\u3002\u6211\u7684\u5de5\u4f5c\u5c31\u662f\u6709\u4ef7\u503c\u7684\u3002\u795d\u798f\u6211\u4eec\u76842015. \u795d\u798f\u4e2d\u56fd\u3002PDF\u4e0b\u8f7d URL\uff1a1. \u65b0\u6d6avdisk\uff1a<a href=\"http://t.cn/RZyBgZP\" target=\"_blank\">http://t.cn/RZyBgZP</a> \u6216\u8005 2. \u5f2f\u66f2\u8bc4\u8bba\uff1a<a href=\"http://t.cn/RZyBgvL\" target=\"_blank\">http://t.cn/RZyBgvL</a>", "poster_name": "@\u6e7e\u533a\u8bc4\u8bba", "profile_photo": "http://tp4.sinaimg.cn/1645518723/50/5686455969/1", "poster_link": "http://weibo.com/1645518723", "post_time": "2014-12-31", "img_url": "http://ww1.sinaimg.cn/large/62149f83jw1ensq87dzvgj20b80dldg2.jpg", "original_link": "http://weibo.com/1645518723/BDmt1up4s"}, {"img_size": "600,375", "text": "\u30102015\uff0cGoogle \u7684 to do list\u3011\u548c\u53bb\u5e74\u4e00\u6837\uff0c\u4eca\u5e74 Google \u505a\u4e86\u5f88\u591a\u4e8b\u60c5\uff0c\u591a\u5230\u6709\u70b9\u6570\u4e0d\u6e05\u3002ArsTechnica \u505a\u4e86\u8be6\u7ec6\u7684\u68b3\u7406\uff0c\u6574\u7406\u4e86 Google \u4eca\u5e74\u6536\u8d2d\u7684\u516c\u53f8\u4ee5\u53ca\u4e4b\u540e\u6240\u505a\u7684\u52a8\u4f5c\uff0c\u77e5\u9053\u5b83\u5728\u4e0b\u4e00\u5e74\u7684\u6253\u7b97\u3002<a href=\"http://t.cn/RZL8cwK\" target=\"_blank\">http://t.cn/RZL8cwK</a>", "poster_name": "@\u683c\u7075\u6df1\u77b3", "profile_photo": "http://tp1.sinaimg.cn/3769368692/50/40061831206/1", "poster_link": "http://weibo.com/3769368692", "post_time": "2014-12-31", "img_url": "http://ww4.sinaimg.cn/large/e0ac0074gw1ensmw7sl6aj20go0af40k.jpg", "original_link": "http://weibo.com/3769368692/BDmfibumu"}, {"retweet_text": "\u300aRedis\u547d\u4ee4\u53c2\u8003\u300b\u6587\u6863\u66f4\u65b0\uff0c\u65b0\u6dfb\u52a0HyperLogLog\u6570\u636e\u7ed3\u6784\u547d\u4ee4 PFADD\u3001PFCOUNT \u548c PFMERGE \uff0c\u4ee5\u53ca\u4e09\u4e2a\u6709\u5e8f\u96c6\u5408\u547d\u4ee4 ZRANGEBYLEX\u3001ZLEXCOUNT \u548c ZREMRANGEBYLEX\uff0c\u8be6\u7ec6\u8bf7\u89c1\uff1a <a href=\"http://t.cn/RvuByeK\" target=\"_blank\">http://t.cn/RvuByeK</a>", "post_time": "2014-12-31", "retweet_poster_link": "http://weibo.com/3219474004", "text": "Redis\u5185\u7f6e\u652f\u6301HyperLogLog\u4e86 //@\u9ec4\u5065\u5b8f_huangz: Redis \u4ece 2.8.9 \u5f00\u59cb\u652f\u6301 HyperLogLog \u7ed3\u6784\uff0c\u8be5\u7ed3\u6784\u53ef\u4ee5\u5c06\u7edf\u8ba1\u5927\u91cf\u5143\u7d20\u6240\u9700\u7684\u5185\u5b58\u4ece\u6570\u5341 GB\u3001\u6570\u767e GB \u964d\u4f4e\u4e3a 12 KB\uff0c\u60f3\u77e5\u9053 HyperLogLog \u4e3a\u4ec0\u4e48\u8fd9\u4e48\u68d2\uff0c\u53ef\u4ee5\u53c2\u8003 Redis \u4f5c\u8005\u5199\u7684\u535a\u6587\uff1a <a href=\"http://t.cn/8sx6WpJ\" target=\"_blank\">http://t.cn/8sx6WpJ</a>", "poster_name": "@\u597d\u4e1c\u897f\u4f20\u9001\u95e8", "profile_photo": "http://tp1.sinaimg.cn/5220650532/50/5701668539/1", "poster_link": "http://weibo.com/5220650532", "retweet_poster_name": "@\u9ec4\u5065\u5b8f_huangz", "original_link": "http://weibo.com/5220650532/BDm5Hn7z9"}, {"img_size": "600,378", "text": "\u5fae\u4fe1\u5b98\u65b9\u6570\u636e\u62ab\u9732\uff1a\u4ec0\u4e48\u6837\u7684\u6587\u7ae0\u66f4\u53d7\u6b22\u8fce <a href=\"http://t.cn/RZL78jd\" target=\"_blank\">http://t.cn/RZL78jd</a> ", "poster_name": "@DataMooc", "profile_photo": "http://tp4.sinaimg.cn/1649885883/50/5656984412/1", "poster_link": "http://weibo.com/1649885883", "post_time": "2014-12-31", "img_url": "http://ww2.sinaimg.cn/large/625742bbjw1ensnr1lovrj20go0aidh7.jpg", "original_link": "http://weibo.com/1649885883/BDlSsvJAh"}, {"img_size": "961,634", "text": "LaTeX\u5de5\u4f5c\u5ba4\u66f4\u65b0\uff1a \u300aLaTeX\u6392\u7248\u7684\u8ba1\u7b97\u673a\u7a0b\u5e8f\u7684\u6784\u9020\u4e0e\u89e3\u91ca(SICP)\u300b <a href=\"http://t.cn/RZyHimZ\" target=\"_blank\">http://t.cn/RZyHimZ</a> SICP\u88ab\u4e16\u754c\u4e0a\u4e00\u4e9b\u6700\u8457\u540d\u7684\u5927\u5b66\uff08\u5982\u65af\u5766\u798f\u3001\u666e\u6797\u65af\u987f\u3001\u725b\u6d25\u7b49\uff09\u7528\u4f5c\u7a0b\u5e8f\u8bbe\u8ba1\u8bfe\u7a0b\u7684\u6559\u6750\uff0c\u88ab\u5e7f\u6cdb\u79f0\u8a89\u4e3a...", "poster_name": "@LaTeX\u79d1\u6280\u6392\u7248", "profile_photo": "http://tp4.sinaimg.cn/1578561911/50/1300160113/0", "poster_link": "http://weibo.com/1578561911", "post_time": "2014-12-31", "img_url": "http://ww2.sinaimg.cn/large/5e16f177jw1ensnfqp31uj20qp0hmq5i.jpg", "original_link": "http://weibo.com/1578561911/BDlO3dnvH"}, {"post_time": "2014-12-31", "text": "Web\u6280\u672f\u65e5\u62a5 2014-12-30 <a href=\"http://t.cn/RZyTSQw\" target=\"_blank\">http://t.cn/RZyTSQw</a> 1) Cocos2d-JS v3.2\u91cd\u6784Web\u5f15\u64ce\u7684\u6e32\u67d3\u5668 2) ECUG\uff08\u5b9e\u6548\u4e91\u8ba1\u7b97\u7528\u6237\u7ec4\uff09\u4e13\u9898\u56de\u987ePPT 3) Material design\u975e\u5b98\u65b9\u4e2d\u6587\u6307\u5bfc\u624b\u518c 4) \u300aCSS Secrets\u300b 5) fibjs \u548c nodejs \u5e76\u53d1\u6a21\u578b\u4e0a\u7684\u5dee\u5f02\u6027\u5206\u6790 \u53ef\u70b9\u51fb\u52a0\u957f\u724840\u6761 <a href=\"http://t.cn/RZyTKrB\" target=\"_blank\">http://t.cn/RZyTKrB</a>", "poster_name": "@\u597d\u4e1c\u897f\u4f20\u9001\u95e8", "profile_photo": "http://tp1.sinaimg.cn/5220650532/50/5701668539/1", "poster_link": "http://weibo.com/5220650532", "original_link": "http://weibo.com/5220650532/BDlKuqrAR"}, {"post_time": "2014-12-31", "text": "#Go\u6280\u672f\u6668\u8bfb#\u5feb\u901f\u6392\u5e8f\u7b97\u6cd5\uff0c\u5e73\u5747\u72b6\u51b5\u4e0b\uff0c\u6392\u5e8f\u8981\u039f(nlogn)\u6b21\u6bd4\u8f83\u3002\u5728\u6700\u574f\u72b6\u51b5\u4e0b\u5219\u9700\u8981\u039f(n2)\u6b21\u6bd4\u8f83\uff0c\u4f46\u4e0d\u5e38\u89c1\u3002\u4e8b\u5b9e\u4e0a\uff0c\u5feb\u901f\u6392\u5e8f\u901a\u5e38\u660e\u663e\u6bd4\u5176\u4ed6\u039f(nlogn)\u7b97\u6cd5\u66f4\u5feb\uff0c\u56e0\u4e3a\u5b83\u7684\u5185\u90e8\u5faa\u73af\uff08inner loop\uff09\u53ef\u4ee5\u5728\u5927\u90e8\u5206\u7684\u67b6\u6784\u4e0a\u5f88\u6709\u6548\u7387\u5730\u88ab\u5b9e\u73b0\u51fa\u6765\u3002\u672c\u6587\u7528Go\u8bed\u8a00\u5b9e\u73b0\u5feb\u901f\u6392\u5e8f\uff0c\u8fd8\u6709\u89c6\u9891 <a href=\"http://t.cn/RZyjMCO\" target=\"_blank\">http://t.cn/RZyjMCO</a>", "poster_name": "@GO\u8bed\u8a00\u4e2d\u6587\u7f51", "profile_photo": "http://tp4.sinaimg.cn/3169236923/50/5649226832/1", "poster_link": "http://weibo.com/3169236923", "original_link": "http://weibo.com/3169236923/BDlCbnsfV"}, {"retweet_text": "Kaggle\u8fbe\u4ebaYANIR SEROUSSI\u544a\u8bc9\u4f60\u5982\u4f55\u9009\u62e9Stochastic Gradient Boosting\u7684\u8bad\u7ec3\u6700\u4f73iteration\u8d85\u53c2\u6570\uff1a<a href=\"http://t.cn/RZy9ZZb\" target=\"_blank\">http://t.cn/RZy9ZZb</a> @\u6881\u658cpenny", "retweet_img_size": "858,643", "post_time": "2014-12-31", "retweet_poster_link": "http://weibo.com/1657470871", "retweet_img_url": "http://ww3.sinaimg.cn/large/62caff97jw1ensk4t69zij20nu0hvdh9.jpg", "text": "//@LR\u673a\u5668\u5b66\u4e60\u8ba1\u7b97\u673a\u89c6\u89c9://@\u6570\u76df\u793e\u533a://@\u9648\u5929\u5947\u602a: \u5176\u5b9e\u4e00\u822c\u6570\u636e\u89c4\u6a21\u8db3\u591fgbtree\u90fd\u662f\u8f6e\u6570\u8d8a\u591a\u8d8a\u597d\uff0c\u4e0d\u9700\u8981\u9009\u8f6e\u6570\u7684", "poster_name": "@hbyido", "profile_photo": "http://tp4.sinaimg.cn/1646706835/50/5697375631/1", "poster_link": "http://weibo.com/1646706835", "retweet_poster_name": "@\u738b\u5a01\u5ec9", "original_link": "http://weibo.com/1646706835/BDlAy4BHh"}, {"retweet_text": "\u3010\u7ed9\u7a0b\u5e8f\u733f\u6700\u597d\u7684\u65b0\u5e74\u793c\u7269\u3011\u5e73\u5b89\u591c\u522b\u4eba\u5237\u5c4f\uff0c\u4f60coding\uff1f\u5723\u8bde\u8282\u522b\u4eba\u6536\u793c\uff0c\u4f60debug? \u773c\u770b\u5143\u65e6\u53c8\u6765\u4e86\uff0c\u6574\u4e2a\u4eba\u90fd\u4e0d\u597d\u4e86\u3002\u7a0b\u5e8f\u733f\u522b\u54ed\uff0c\u4fdd\u969c\u541b\u5fc3\u75bc\u4f60\uff0c\u6700\u8d34\u5fc3\u7684\u65b0\u5e74\u5927\u793c\u62ff\u53bb - \u7528\u4e86\u90fd\u8bf4\u597d\u7684\u963f\u91cc\u5f00\u6e90\u955c\u50cf\u7f51\u7ad9 <a href=\"http://t.cn/8kdwImh\" target=\"_blank\">http://t.cn/8kdwImh</a>", "retweet_img_size": "440,4086", "post_time": "2014-12-31", "retweet_poster_link": "http://weibo.com/3851645388", "retweet_img_url": "http://ww3.sinaimg.cn/large/e59371ccgw1enq915wq03j20c835idw2.jpg", "text": "\u76f4\u63a5\u8f6c\u7ed9Ali-OSM\u7684\u5f00\u53d1\u5de5\u7a0b\u5e08\u4e03\u8d24\u770b\u770b \uff0c\u8c61\u8fd9\u6837\u7684\u9700\u6c42\uff0c\u90fd\u6b22\u8fce\u76f4\u63a5\u627e\u4e03\u8d24GG @qqeyes //@qinjianxiang: \u80fd\u7ed9PHP\u7684remi yum repo\u505a\u4e2a\u955c\u50cf\u5417\uff1f\u5730\u5740\uff1arpms.famillecollet.com", "poster_name": "@\u963f\u91cc\u6280\u672f\u4fdd\u969c", "profile_photo": "http://tp1.sinaimg.cn/3851645388/50/40059402991/1", "poster_link": "http://weibo.com/3851645388", "retweet_poster_name": "@\u963f\u91cc\u6280\u672f\u4fdd\u969c", "original_link": "http://weibo.com/3851645388/BDlvEAzAG"}, {"retweet_text": "#ECUG Con#\u4eca\u5929\u7ee7\u7eed\u7ed9\u5927\u5bb6\u5206\u4eabECUG Con 2014\u5927\u4f1a\u7684\u5e72\u8d27\u3002\u4eca\u5929\u5206\u4eab\u7684\u662f\uff1a\u7530\u742a\uff08\u4eac\u4e1c\u8d44\u6df1\u67b6\u6784\u5e08\uff09\u3001\u4f55\u5168\uff08\u591a\u5907\u4efd\u6280\u672f\u603b\u76d1\uff09\u3001\u9a6c\u5168\u4e00\uff08docker.cn\u521b\u59cb\u4eba\uff09\u3001\u8c22\u5b5f\u519b\uff08beego\u4f5c\u8005\uff0cgo web\u7f16\u7a0b\u4f5c\u8005\uff09\u4ee5\u53ca\u6768\u7ae0\u663e\uff08\u5c31\u804c\u4e8eCisco\uff0c\u4e91\u8ba1\u7b97\u5f00\u6e90\u6280\u672f\u7231\u597d\u8005\uff09\u7b495\u4f4d\u8bb2\u5e08\u7684\u7cbe\u5f69\u6f14\u8bb2\u3002\u8be6\u60c5\u8bf7\u6233\uff1a<a href=\"http://t.cn/RZAWdZM\" target=\"_blank\">http://t.cn/RZAWdZM</a>", "retweet_img_size": "440,2106", "post_time": "2014-12-31", "retweet_poster_link": "http://weibo.com/2651079901", "retweet_img_url": "http://ww1.sinaimg.cn/large/9e0444ddgw1enrvvn5qsdj20c81min95.jpg", "text": "\u8fd0\u7ef4\u548c\u67b6\u6784\u5fc5\u8bfb\u3002\u300a\u57fa\u4e8e Ansible \u81ea\u52a8\u5316\u8fd0\u7ef4\u5b9e\u8df5\u300b\u300a\u8c4c\u8c46\u835a\u5206\u5e03\u5f0fredis\u8bbe\u8ba1\u4e0e\u5b9e\u73b0\u300b\u300a\u6df1\u5165\u7406\u89e3Docker\u7684\u67b6\u6784\u4e0e\u5b9e\u73b0\u300b\u300afibjs vs. nodejs\uff1a\u5e76\u53d1\u6a21\u578b\u4e0a\u7684\u5dee\u5f02\u6027\u5206\u6790\u300b\u300a\u4f7f\u7528SaltStack\u90e8\u7f72OpenStack\u7684\u8fd0\u7ef4\u5b9e\u8df5\u300b....\u90fd\u662f\u597d\u4e1c\u897f\u554a\uff01", "poster_name": "@\u597d\u4e1c\u897f\u4f20\u9001\u95e8", "profile_photo": "http://tp1.sinaimg.cn/5220650532/50/5701668539/1", "poster_link": "http://weibo.com/5220650532", "retweet_poster_name": "@\u4e03\u725b\u4e91\u5b58\u50a8", "original_link": "http://weibo.com/5220650532/BDlsbahYQ"}, {"post_time": "2014-12-31", "text": "\u63a8\u8350\uff0c\u63a8\u8350\uff01 \u6df1\u5ea6\u5b66\u4e60\u9605\u8bfb\u6e05\u5355 <a href=\"http://t.cn/RZypeZw\" target=\"_blank\">http://t.cn/RZypeZw</a>", "poster_name": "@\u5dee\u54e5", "profile_photo": "http://tp3.sinaimg.cn/1676039502/50/5698456497/1", "poster_link": "http://weibo.com/1676039502", "original_link": "http://weibo.com/1676039502/BDlkLlUo1"}, {"img_size": "600,371", "text": "\u7ef4\u57fa\u767e\u79d1\u5ba3\u5e03\uff0c\u5df2\u5c06\u6240\u6709\u670d\u52a1\u5668\u7684PHP\u5f15\u64ce\uff0c\u4eceZend\u53d8\u4e3aHHVM\uff0c\u5e73\u5747\u9875\u9762\u52a0\u8f7d\u65f6\u95f4\u4ece1.3\u79d2\u53d8\u4e3a0.9\u79d2\uff0c\u5e73\u5747\u9875\u9762\u4fdd\u5b58\u65f6\u95f4\uff08\u5b58\u5165\u6570\u636e\u5e93\uff09\u4ece6\u79d2\u53d8\u4e3a3\u79d2\uff0cCPU\u8d1f\u8f7d\u4ece50%\u964d\u4e3a10% <a href=\"http://t.cn/RZy5lib\" target=\"_blank\">http://t.cn/RZy5lib</a>", "poster_name": "@ruanyf", "profile_photo": "http://tp3.sinaimg.cn/1400854834/50/39996025735/1", "poster_link": "http://weibo.com/1400854834", "post_time": "2014-12-31", "img_url": "http://ww1.sinaimg.cn/large/537f5932gw1enslbhmqkuj20go0abmxn.jpg", "original_link": "http://weibo.com/1400854834/BDlkjhqVE"}, {"retweet_text": "A Glimpse into Computer Vision\uff1a #DeepMind#\u4e8e\u89c6\u89c9\u65b9\u9762\u7684\u8fdb\u5c55\uff0c\u53d1\u8868\u4e8e#NIPS2014#\uff0c\u53c2\u89c1 <a href=\"http://t.cn/RZLtxi9\" target=\"_blank\">http://t.cn/RZLtxi9</a>", "post_time": "2014-12-31", "retweet_poster_link": "http://weibo.com/2475016390", "text": "//@vinW://@\u5218\u77e5\u8fdcTHU: //@\u597d\u4e1c\u897f\u4f20\u9001\u95e8: Recurrent Models of Visual Attention <a href=\"http://t.cn/RZyXsJV\" target=\"_blank\">http://t.cn/RZyXsJV</a> by Volodymyr Mnih, Nicolas Heess, Alex Graves, Koray Kavukcuoglu", "poster_name": "@hbyido", "profile_photo": "http://tp4.sinaimg.cn/1646706835/50/5697375631/1", "poster_link": "http://weibo.com/1646706835", "retweet_poster_name": "@3A\u72d7\u72d7", "original_link": "http://weibo.com/1646706835/BDlgzEBgn"}, {"post_time": "2014-12-31", "text": "Python\u65e5\u62a5 2014-12-30 <a href=\"http://t.cn/RZyNzBD\" target=\"_blank\">http://t.cn/RZyNzBD</a> 1) measurement\uff1a\u5355\u4f4d\u8f6c\u6362\u4e0e\u7b97\u672f 2) PHP\u8c03\u8bd5Python 3) \u5f00\u53d1\u73af\u5883\u548cDjango\u5b89\u88c5 4) Python\u7f16\u7a0b\u8bed\u8a00\u7684\u53d1\u5c55\u7b80\u53f2 5) qyuhen Python \u5b66\u4e60\u7b14\u8bb0 \u7b2c\u4e8c\u7248 \u53ef\u70b9\u51fb\u52a0\u957f\u724817\u6761 <a href=\"http://t.cn/RZyNwWA\" target=\"_blank\">http://t.cn/RZyNwWA</a>", "poster_name": "@\u597d\u4e1c\u897f\u4f20\u9001\u95e8", "profile_photo": "http://tp1.sinaimg.cn/5220650532/50/5701668539/1", "poster_link": "http://weibo.com/5220650532", "original_link": "http://weibo.com/5220650532/BDlcPDCuf"}, {"img_size": "500,293", "text": "\u3010\u81ea\u5b9a\u4e49\u5143\u7d20\u2013\u4e3a\u4f60\u7684HTML\u4ee3\u7801\u5b9a\u4e49\u65b0\u5143\u7d20\u3011 \u81ea\u5b9a\u4e49\u5143\u7d20\u4e3a\u6211\u4eec\u63d0\u4f9b\u4e86\u4e00\u4e2a\u5de5\u5177\uff0c\u901a\u8fc7\u5b83\u6211\u4eec\u53ef\u4ee5\u6269\u5c55 HTML \u7684\u8bcd\u6c47\uff0c\u8d4b\u4e88\u5b83\u65b0\u7684\u7279\u6027\uff0c\u5e76\u628a\u4e0d\u540c\u7684 web \u5e73\u53f0\u8fde\u63a5\u5728\u4e00\u8d77\u3002\u7ed3\u5408\u5176\u4ed6\u65b0\u7684\u57fa\u672c\u5e73\u53f0\uff0c\u5982 Shadow DOM \u548c templ... \u8be6\u89c1\uff1a<a href=\"http://t.cn/RzaTjew\" target=\"_blank\">http://t.cn/RzaTjew</a>", "poster_name": "@IT\u6280\u672f\u535a\u5ba2\u5927\u5b66\u4e60", "profile_photo": "http://tp1.sinaimg.cn/1646218964/50/1279883225/1", "poster_link": "http://weibo.com/1646218964", "post_time": "2014-12-31", "img_url": "http://ww4.sinaimg.cn/large/621f4ed4jw1ensjrkb5gtj20dw085mz6.jpg", "original_link": "http://weibo.com/1646218964/BDkYugCe7"}, {"post_time": "2014-12-31", "text": "\u673a\u5668\u5b66\u4e60\u65e5\u62a5 2014-12-30 <a href=\"http://t.cn/RZyoeCe\" target=\"_blank\">http://t.cn/RZyoeCe</a> 1) \u8ba8\u8bba\uff1a\u5e7f\u544a\u548c\u4e2a\u6027\u5316\u63a8\u8350 2) \u5927\u89c4\u6a21\u5e76\u884c\u673a\u5668\u5b66\u4e60\u8ba1\u7b97\u6846\u67b6 Petuum 3) Kaggle \u673a\u5668\u5b66\u4e60\u7ade\u8d5b\u51a0\u519b\u53ca\u4f18\u80dc\u8005\u7684\u6e90\u4ee3\u7801\u6c47\u603b 4) ICML 2014\u4e0a\u7684\u89c6\u9891 5) \u56de\u987e\uff1a\u5982\u679c\u9ed1\u5ba2\u63a7\u5236\u4e86\u8bad\u7ec3\u6837\u672c \u53ef\u70b9\u51fb\u52a0\u957f\u724845\u6761 <a href=\"http://t.cn/RZyoDBE\" target=\"_blank\">http://t.cn/RZyoDBE</a>", "poster_name": "@\u597d\u4e1c\u897f\u4f20\u9001\u95e8", "profile_photo": "http://tp1.sinaimg.cn/5220650532/50/5701668539/1", "poster_link": "http://weibo.com/5220650532", "original_link": "http://weibo.com/5220650532/BDkXD2JAI"}, {"img_size": "687,3358", "text": "\u3010\u7ffb\u6eda\u5427\uff1aSpark\u3011\u5f53 Spark \u6210\u4e3a\u4e3b\u89d2\u540e\uff0c\u4e0b\u4e00\u4ee3\u5927\u6570\u636e\u5206\u6790\u53ef\u5206\u4e3a\u4e24\u7c7b\uff1a\u4e00\u662f\u7c7b\u4f3cSQL\u6570\u636e\u5206\u6790\uff0c\u8fdb\u884c\u5173\u7cfb\u578b\u4e91\u8fd0\u7b97\uff1b\u4e8c\u662f\u8fbe\u5230\u5b9e\u65f6\u3001\u5feb\u901f\u7684\u6570\u636e\u5206\u6790\u901f\u5ea6\u3002 <a href=\"http://t.cn/RZyoZyX\" target=\"_blank\">http://t.cn/RZyoZyX</a> #\u82f1\u773c\u770bIT#", "poster_name": "@\u82f1\u7279\u5c14\u5546\u7528\u9891\u9053", "profile_photo": "http://tp2.sinaimg.cn/2295615873/50/5709954620/1", "poster_link": "http://weibo.com/2295615873", "post_time": "2014-12-31", "img_url": "http://ww2.sinaimg.cn/large/88d45181jw1ensjdtys3aj20j32lakej.jpg", "original_link": "http://weibo.com/2295615873/BDkT8qt4d"}, {"post_time": "2014-12-31", "text": "@ICT_\u6731\u4e9a\u4e1c \u53d1\u8d77\u7684\u8ba8\u8bba\u300a\u5e7f\u544a\u548c\u4e2a\u6027\u5316\u63a8\u8350\u300b1\uff1a\u5e7f\u544a\u7684\u67b6\u6784\u7b56\u7565\u6d41\u7a0b\u771f\u7684\u80fd\u62ff\u6765\u505a\u4e2a\u6027\u5316\u63a8\u8350\u4e48\uff1f2\uff1a\u4e3a\u4ec0\u4e48\u5e7f\u544a\u91cc\u901a\u5e38\u91c7\u7528ID\u7c7b\u7279\u5f81\u7684\u8868\u793a\u65b9\u6cd5\uff1f@\u5f20\u9896\u5cf0 \u8bf4\u63a8\u8350\u4e00\u822c\u662f\u4e00\u5806\u7b56\u7565\u7684\u5408\u6210\uff0c\u5e7f\u544a\u76f8\u5bf9\u5355\u4e00 @\u5b59\u660e\u660e_SmarterChina \u8bf4\u8d8b\u52bf\u662f\u79bb\u6563/\u8fde\u7eed\u7279\u5f81\u7ed3\u5408\u3002\u8be6\u60c5\u8bf7\u770b\u673a\u5668\u5b66\u4e60\u65e5\u62a5\u53f7\u5916<a href=\"http://t.cn/RZy61Pe\" target=\"_blank\">http://t.cn/RZy61Pe</a>", "poster_name": "@\u597d\u4e1c\u897f\u4f20\u9001\u95e8", "profile_photo": "http://tp1.sinaimg.cn/5220650532/50/5701668539/1", "poster_link": "http://weibo.com/5220650532", "original_link": "http://weibo.com/5220650532/BDkzQxJ3p"}, {"post_time": "2014-12-31", "text": "\u79fb\u52a8\u7aef\u524d\u7aef\u5f00\u53d1\u8c03\u8bd5 <a href=\"http://t.cn/RvCEWqi\" target=\"_blank\">http://t.cn/RvCEWqi</a>\u3002\u521a\u91cd\u65b0\u6574\u7406\u5b8c\uff0c\u7761\u4e86\u3002  ", "poster_name": "@\u4e8e\u6c5f\u6c34", "profile_photo": "http://tp1.sinaimg.cn/2945647940/50/5702288820/1", "poster_link": "http://weibo.com/2945647940", "original_link": "http://weibo.com/2945647940/BDhXb8of0"}]